Workbook

Sheet Synthèse
E3: SYNTHESE NUMERIQUE
A5: N° | B5: Domaines | C5: Total OUI | D5: Total NON | E5: Total PAS | F5: Total | G5: Score
A6: 1 | B6: Application en service | C6: =COUNTIF('4.1'!J2:J147,"OUI") -> 84 | D6: =COUNTIF('4.1'!J2:J147,"NON") -> 3 | E6: =COUNTIF('4.1'!J2:J147,"PAS") -> 59 | F6: =SUM(C6:E6) -> 146 | G6: =D6/F6 -> 0.020547945
A7: 2 | B7: Fonction informatique | C7: =COUNTIF('4.2'!F2:F141,"OUI") -> 74 | D7: =COUNTIF('4.2'!F2:F141,"NON") -> 8 | E7: =COUNTIF('4.2'!F2:F141,"PAS") -> 58 | F7: =SUM(C7:E7) -> 140 | G7: =D7/F7 -> 0.057142857
A8: 3 | B8: Projet informatique | C8: =COUNTIF('4.3'!F2:F476,"OUI") -> 339 | D8: =COUNTIF('4.3'!F2:F476,"NON") -> 63 | E8: =COUNTIF('4.3'!F2:F476,"PAS") -> 73 | F8: =SUM(C8:E8) -> 475 | G8: =D8/F8 -> 0.13263158
A9: 4 | B9: SUPPORT UTILISATEUR ET GESTON DU PARC | C9: =COUNTIF('4.4'!F2:F121,"OUI") -> 79 | D9: =COUNTIF('4.4'!F2:F121,"NON") -> 9 | E9: =COUNTIF('4.4'!F2:F121,"PAS") -> 32 | F9: =SUM(C9:E9) -> 120 | G9: =D9/F9 -> 0.075
A10: 5 | B10: SECURITE INFORMATIQUE | C10: =COUNTIF('4.5'!F2:F286,"OUI") -> 137 | D10: =COUNTIF('4.5'!F2:F286,"NON") -> 38 | E10: =COUNTIF('4.5'!F2:F286,"PAS") -> 110 | F10: =SUM(C10:E10) -> 285 | G10: =D10/F10 -> 0.13333333
A11: TOTAL | C11: =SUM(C6:C10) -> 713 | D11: =SUM(D6:D10) -> 121 | E11: =SUM(E6:E10) -> 332 | F11: =SUM(F6:F10) -> 1166 | G11: =SUM(G6:G10) -> 0.41865571
C12: SYNTHESE GRAPHIQUE

Sheet Global

Sheet 4.1
A1: DOMAINES | B1: RESPONSABLES | C1: DUREE | D1: MOYENS POUR LA REALISATION | E1: PARTIE PRENANTES | F1: POINTS DE CONTRÔLE | G1: OBJECTIFS DE CONTRÔLE | H1: CRITERES D'EVALUATION | I1: QUESTIONS D'EVALUATION | J1: REPONSES | K1: DOCUMENTS REQUIS | L1: RISQUES | M1: CRITICITE | N1: CONSEQUENCES | O1: RECOMMANDATIONS
A2: Applications en services | F2: Organisation | G2: S’assurer de l’existence d'un comité informatique | H2: Existence d'un comité informatique ; | I2: Existe-t-il un comité informatique ? | J2: OUI | K2: Charte du comité informatique, comptes rendus des réunions du comité informatique | L2: Absence de comité ou comité inactif | M2: Élevé | N2: Décisions informatiques non alignées avec les besoins des utilisateurs et les objectifs stratégiques de l'institution. | O2: Mettre en place des ateliers réguliers avec les parties prenantes.
H3: Le Comité est présidé par le Directeur Général ; | I3: Le Comité est-il présidé par le directeur général? | J3: OUI | K3: Organigramme de l'entreprise, procès-verbaux des réunions du comité informatique | L3: Manque d'expertise technique du DG | M3: Élevé | N3: Manque de coordination et de communication entre les différentes directions utilisatrices concernant les applications. | O3: Instaurer des canaux de communication formels inter-départements.
H4: Les directions utilisatrices sont représentées au sein de ce Comité ; | I4: Les directions utilisatrices sont-elles représentées au sein de ce comité ? | J4: OUI | K4: Liste des membres du comité informatique, mandats de représentation | L4: Représentation insuffisante ou inefficace des directions utilisatrices | M4: Élevé | N4: Prise de décisions informatiques unilatérales par la direction générale, sans prise en compte des besoins des utilisateurs. | O4: Établir un comité consultatif incluant des représentants des utilisateurs ou syndicat.
H5: Les directions utilisatrices sont influentes au sein de ce Comité. | I5: Les directions utilisatrices sont-elles influentes au sein de ce Comité? | J5: PAS | K5: Procès-verbaux des réunions du comité informatique, sondages ou évaluations de l'efficacité du comité | L5: Objectifs divergents des directions utilisatrices et de la direction informatique | M5: Élevé | N5: Influence disproportionnée de certaines directions utilisatrices sur les décisions relatives aux applications, au détriment des autres. | O5: Créer un cadre de gouvernance équilibré.
H6: Fréquence régulière des réunions et existence de comptes rendus | I6: Quelle est la fréquence régulière des réunions et existe-t-il des comptes rendus? | J6: OUI | K6: Calendrier des réunions du comité informatique, modèle de compte rendu standardisé | L6: Réunions irrégulières ou comptes rendus incomplets | M6: Élevé | N6: Manque de suivi et de contrôle des décisions prises lors des réunions, absence de traçabilité. | O6: Mettre en place un système de documentation et de suivi.
G7: S’assurer de l’existence d'une politique relative aux applications | H7: Il existe une politique relative aux applications au sein de l'institution ; | I7: Existe-t-il une politique relative aux applications au sein de l'institution ? | J7: OUI | K7: Document de politique des applications, attestations de lecture et de compréhension de la politique | L7: Politique obsolète ou inadaptée aux nouvelles technologies | M7: Élevé | N7: Mise en place d'applications non conformes aux besoins des utilisateurs et aux objectifs de l'institution. | O7: Effectuer des analyses de besoins approfondies.
H8: La politique est connue des utilisateurs d'applications ; | I8: La politique est-elle connue des utilisateurs d'applications ? | J8: OUI | K8: Liste de diffusion de la politique, captures d'écran ou liens vers les supports de diffusion | L8: Manque de sensibilisation ou de formation des utilisateurs | M8: Élevé | N8: Méconnaissance des politiques relatives aux applications par les utilisateurs, non-respect des règles établies. | O8: Organiser des sessions de formation régulières.
H9: La politique est largement diffusée ; | I9: La politique est-elle largement diffusée ? | J9: OUI | K9: Registre des non-conformités et des actions correctives, rapports d'audit de conformité | L9: Méthodes de diffusion inefficaces | M9: Élevé | N9: Diffusion restreinte des politiques, manque de transparence et d'accessibilité. | O9: Publier les politiques sur une plateforme accessible.
H10: La politique est mise en œuvre ; | I10: La politique est-elle mise en œuvre ? | J10: OUI | K10: Tableau de correspondance entre la politique et les phases du cycle de vie, modèles de documents pour chaque phase du cycle de vie | L10: Manque de suivi et de contrôle de l'application de la politique | M10: Élevé | N10: Non-application des politiques, inefficacité des règles établies. | O10: Établir des mécanismes de contrôle pour assurer la conformité.
H11: La politique couvre l'ensemble du cycle de vie de l’application ; | I11: La politique couvre-t-elle l'ensemble du cycle de vie de l’application ? | J11: NON | K11: Description des rôles et responsabilités dans la politique ou les procédures, matrice RACI (Responsable, Approbateur, Consulté, Informé) | L11: Lacunes dans certaines phases du cycle de vie de l'application | M11: Élevé | N11: Applications obsolètes ou non adaptées aux besoins actuels, manque de maintenance. | O11: Mettre en place un programme de mise à jour régulière.
G12: S’assurer que les rôle et responsabilités des utilisateurs sont bien définis | H12: Le rôle et les responsabilités des utilisateurs vis-à-vis de l’application sont clairement identifiés ; | I12: Le rôle et les responsabilités des utilisateurs vis-à-vis de l’application sont-ils clairement identifiés ? | J12: NON | K12: Procédure d'analyse des risques, modèles de rapports d'analyse des risques | L12: Ambiguïté des rôles et responsabilités des utilisateurs | M12: Élevé | N12: Mauvaise compréhension des rôles et responsabilités des utilisateurs, manque de clarté. | O12: Clarifier et documenter les rôles et responsabilités.
H13: Le rôle et les responsabilités des utilisateurs vis-à-vis de l’application couvrent l’analyse des risques ; | I13: Le rôle et les responsabilités des utilisateurs vis-à-vis de l’application couvrent-ils l’analyse des risques ? | J13: NON | K13: Procédure de définition des besoins de sécurité, modèles de cahiers des charges fonctionnels et techniques | L13: Manque de compétences des utilisateurs en matière d'analyse des risques | M13: Élevé | N13: Absence de prise en compte des risques liés à l'application par les utilisateurs, vulnérabilités non identifiées. | O13: Intégrer une évaluation des risques dans le développement.
H14: Le rôle et les responsabilités des utilisateurs vis-à-vis de l’application couvrent la définition des besoins de sécurité | I14: Le rôle et les responsabilités des utilisateurs vis-à-vis de l’application couvrent-ils la définition des besoins de sécurité? | J14: OUI | K14: Procédure de gestion des changements, registre des changements | L14: Sous-estimation des besoins de sécurité par les utilisateurs | M14: Élevé | N14: Non-respect des exigences de sécurité lors de la conception et du développement de l'application. | O14: Adopter des pratiques de développement sécurisé.
H15: Le rôle et les responsabilités des utilisateurs vis-à-vis de l’application couvrent la gestion des changements et des évolutions ; | I15: Le rôle et les responsabilités des utilisateurs vis-à-vis de l’application couvrent-ils la gestion des changements et des évolutions ? | J15: OUI | K15: Guides d'administration, procédure d'administration de l'application | L15: Manque de conscience des risques liés aux changements et évolutions | M15: Élevé | N15: Gestion inefficace des changements et évolutions de l'application, manque de flexibilité. | O15: Mettre en place une gestion des changements rigoureuse.
H16: Le rôle et les responsabilités des utilisateurs vis-à-vis de l’application couvrent l’administration de l’application. | I16: Le rôle et les responsabilités des utilisateurs vis-à-vis de l’application couvrent-ils l’administration de l’application? | J16: OUI | K16: Rapport d'analyse des risques, plan de traitement des risques | L16: Manque de compétences pour administrer l'application | M16: Élevé | N16: Administration déficiente de l'application, problèmes de performance et de disponibilité. | O16: Renforcer l'administration des systèmes.
G17: S’assurer qu’une analyse des risques a été réalisée | H17: Une analyse des risques spécifique à l’application a été réalisée ; | I17: Une analyse des risques spécifique à l’application a-t-elle été réalisée ? | J17: OUI | K17: Tableau de correspondance entre les risques et les besoins de sécurité, cahier des charges fonctionnel et technique | L17: Analyse des risques incomplète ou obsolète | M17: Élevé | N17: Identification insuffisante des risques spécifiques à l'application, vulnérabilités non détectées. | O17: Réaliser des audits de sécurité réguliers.
H18: L'analyse des risques a débouché sur la définition des besoins de sécurité. | I18: L'analyse des risques a-t-elle débouché sur la définition des besoins de sécurité? | J18: OUI | K18: Tableau de bord de suivi des performances, rapports d'analyse des performances | L18: Besoins de sécurité mal définis ou non appliqués | M18: Élevé | N18: Absence de définition des besoins de sécurité, manque de protection des données sensibles. | O18: Établir des exigences de sécurité claires.
H19: Monitoring des performances des services | I19: Y a-t-il un monitoring des performances des services? | J19: OUI | K19: Procédure de gestion des incidents, registre des incidents | L19: Surveillance insuffisante ou inefficace des performances des services | M19: Élevé | N19: Dégradation des performances de l'application, insatisfaction des utilisateurs. | O19: Mettre en place des indicateurs de performance.
H20: Gestion proactive des incidents et mise en place d’un support technique | I20: Y a -t-il une gestion proactive des incidents et mise en place d’un support technique? | J20: OUI | K20: Plan de reprise après sinistre, rapports de tests de reprise après sinistre | L20: Support technique insuffisant ou incompétent | M20: Moyen | N20: Incapacité à résoudre rapidement les incidents, manque de support technique. | O20: Renforcer l'équipe de support technique.
H21: Tests réguliers des procédures de reprise après sinistre | I21: Existe-t-il des tests réguliers des procédures de reprise après sinistre? | J21: PAS | K21: Planning du projet avec les dates des analyses, document de suivi des évolutions des besoins de sécurité | L21: Procédures de reprise après sinistre inefficaces ou non testées | M21: Moyen | N21: Difficultés à reprendre les activités après un sinistre, perte de données et d'informations. | O21: Élaborer un plan de continuité des activités.
G22: S’assurer que le prolongement de l'analyse de risque et de son expansion ont été réalisés | H22: Il y a eu un prolongement de l’analyse des risques et de l’expression des besoins de sécurité | I22: y a-t-il eu un prolongement de l’analyse des risques et de l’expression des besoins de sécurité? | J22: PAS | K22: Document du SLA, rapports de suivi du respect du SLA | L22: Analyse trop longue et besoins de sécurité évoluant plus vite que l'analyse | M22: Moyen | N22: Absence de prise en compte des risques et des besoins de sécurité lors des évolutions de l'application. | O22: Intégrer des évaluations de sécurité.
H23: Un contrat de service (SLA) entre l’informatique et la direction utilisatrice a été mis en œuvre. | I23: Un contrat de service (SLA) entre l’informatique et la direction utilisatrice at-il été mis en œuvre? | J23: PAS | K23: Procédure de journalisation, journaux de transactions | L23: SLA mal défini ou non respecté | M23: Moyen | N23: Non-respect des engagements contractuels, litiges potentiels. | O23: Établir des vérifications régulières de conformité.
H24: Journalisation et suivi des transactions inter-applicatives | I24: Y a-t-il la journalisation et le suivi des transactions inter-applicatives? | J24: PAS | K24: Rapports de tests de sécurité, documentation des mécanismes de chiffrement et d'authentification | L24: Journalisation insuffisante ou journaux non analysés | M24: Élevé | N24: Difficultés à suivre les transactions entre les applications, manque de visibilité. | O24: Mettre en place des outils d'analyse et de reporting.
H25: Vérification des mécanismes de chiffrement et d’authentification | I25: Les mécanismes de chiffrement et d’authentification sont-ils correctement mis en place et vérifiés ? | J25: PAS | K25: Rapports d'audit des interfaces, plan d'action suite aux audits | L25: Mécanismes de chiffrement et d'authentification obsolètes ou mal configurés | M25: Élevé | N25: Vulnérabilités liées aux mécanismes de chiffrement et d'authentification, risques de piratage. | O25: Utiliser des protocoles de sécurité robustes.
H26: Audit des interfaces d’échange de données | I26: Existe-t-il un audit des interfaces d’échange de données? | J26: PAS | K26: Documents de procédures internes, journaux d'activité | L26: Audits insuffisants ou non effectués régulièrement | M26: Élevé | N26: Difficultés à contrôler les échanges de données, risques de fuites d'informations sensibles. | O26: Implémenter des contrôles d'accès stricts.
F27: Application | G27: S'assurer que l'accès aux ressources de l'application (données et transactions) est restreint par un système de gestion d'accès | H27: Il y a une séparation des tâches au sein de la direction utilisatrice indépendamment de l’application ; | I27: Y a-t-il une séparation des tâches au sein de la direction utilisatrice indépendamment de l’application ? | J27: PAS | K27: Documents de procédures internes, journaux d'activité | L27: Manque de séparation des tâches dans la direction utilisatrice | M27: Élevé | N27: Risques d'erreurs et de fraudes liés à la concentration des tâches, manque de contrôle interne. | O27: Séparer les tâches critiques et renforcer les contrôles internes.
H28: Il y a une « maturité » de l’organisation vis-à-vis de ses systèmes d’information. | I28: l’organisation est-elle mature vis-à-vis de ses systèmes d’information? | J28: PAS | K28: Rapports de tests de sécurité, documentation des mécanismes de chiffrement et d'authentification | L28: Faible maturité organisationnelle vis-à-vis des systèmes d'information | M28: Élevé | N28: Manque d'adaptation aux évolutions technologiques, obsolescence des systèmes d'information. | O28: Évaluer régulièrement les technologies.
H29: Implémentation de mesures de chiffrement et de contrôle d’accès | I29: Existe-t-il une implémentation de mesures de chiffrement et de contrôle d’accès? | J29: PAS | K29: Rapports de tests de sécurité, documentation des mécanismes de chiffrement et d'authentification | L29: Absence de chiffrement et de contrôle d'accès | M29: Élevé | N29: Vulnérabilités liées aux accès non autorisés, risques de piratage. | O29: Renforcer les contrôles d'accès.
H30: Contrôle des accès aux données critiques | I30: Existe-t-il un *contrôle des accès aux données critiques? | J30: PAS | K30: Guides d'utilisation de l'application, manuels de formation | L30: Contrôle insuffisant des accès aux données critiques | M30: Élevé | N30: Accès non contrôlés aux données critiques, risques de fuites d'informations sensibles. | O30: Mettre en place des audits réguliers.
H31: Surveillance en temps réel des accès et détection des comportements anormaux | I31: y a-t-il une surveillance en temps réel des accès et détection des comportements anormaux? | J31: OUI | K31: Manuels de formation à l'application, registres de mise à jour des manuels | L31: Surveillance en temps réel des accès et détection de comportements anormaux inexistantes | M31: Élevé | N31: Difficultés à détecter les comportements anormaux, risques de piratage et de fraudes. | O31: Utiliser des outils de surveillance.
G32: S’assurer qu’une procédure de gestion des profils utilisateurs existe | H32: Un ou des manuels pour l’application existe ; | I32: Existe-t-il un ou des manuels pour l’application ? | J32: PAS | K32: Manuels de formation, registres de compétences des utilisateurs | L32: Documentation utilisateur (manuels) manquante ou obsolète | M32: Élevé | N32: Difficultés à utiliser l'application, manque d'autonomie des utilisateurs. | O32: Offrir des formations et des ressources d'apprentissage.
H33: Le manuel est à jour ; | I33: Le manuel est-il à jour ? | J33: PAS | K33: Manuels de formation, guides d'utilisation de l'application | L33: Manuel utilisateur non maîtrisé | M33: Élevé | N33: Informations obsolètes ou incorrectes, risques d'erreurs d'utilisation. | O33: Mettre à jour régulièrement les données.
H34: Le manuel est maitrisé | I34: Le manuel est-il maitrisé? | J34: PAS | K34: Manuels de formation, guides d'administration de l'application | L34: Absence de mode d'emploi dans le manuel | M34: Élevé | N34: Difficultés à comprendre le fonctionnement de l'application, manque d'efficacité. | O34: Fournir des manuels d'utilisation clairs.
H35: Le manuel comprend un mode d'emploi ; | I35: Le manuel comprend-il un mode d'emploi ? | J35: PAS | K35: Procédures de gestion des changements, registres de changements | L35: Manque de documentation sur le module d'administration | M35: Élevé | N35: Difficultés à résoudre les problèmes techniques, dépendance excessive du support informatique. | O35: Créer une base de connaissances.
H36: Le manuel comprend une présentation du module d’administration de l’application ; | I36: Le manuel comprend-il une présentation du module d’administration de l’application ? | J36: PAS | K36: Procédures de gestion des changements, registres de changements | L36: Absence de procédures formalisées pour les changements sur les programmes | M36: Élevé | N36: Difficultés à administrer l'application, manque de contrôle. | O36: Renforcer les processus d'administration.
G37: Vérifier que l’identification des utilisateurs est réalisée | H37: Des procédures formalisées imposant l’accord du « propriétaire » de l’application pour tout changement sur les programmes de l’application existent ; | I37: Des procédures formalisées imposant l’accord du « propriétaire » de l’application pour tout changement sur les programmes de l’application existent-ils? | J37: PAS | K37: Procédures de gestion des changements, registres de changements | L37: Absence de procédures formalisées pour les changements sur la planification | M37: Élevé | N37: Modifications non autorisées des programmes, risques d'erreurs et de fraudes. | O37: Mettre en place un suivi rigoureux des modifications.
H38: Des procédures formalisées imposant l’accord du « propriétaire » de l’application pour tout changement sur la planification des traitements informatiques existent ; | I38: Des procédures formalisées imposant l’accord du « propriétaire » de l’application pour tout changement sur la planification des traitements informatiques existent-ils ? | J38: PAS | K38: Guides d'administration de l'application, registres d'administration | L38: Absence de procédures formalisées pour les changements sur l'environnement technique | M38: Moyen | N38: Planification des tâches non maîtrisée, risques de retards et de dysfonctionnements. | O38: Utiliser des outils de gestion de projet.
H39: Des procédures formalisées imposant l’accord du « propriétaire » de l’application pour tout changement sur l’environnement technologique de l’application existent ; | I39: Des procédures formalisées imposant l’accord du « propriétaire » de l’application pour tout changement sur l’environnement technologique de l’application existent-ils? | J39: PAS | K39: Matrice RACI (Responsable, Approbateur, Consulté, Informé), registres d'habilitation | L39: Administration de l'application non assurée par les utilisateurs | M39: Moyen | N39: Paramétrage incorrect de l'environnement technique, risques de dysfonctionnements. | O39: Établir des procédures de configuration standardisées.
H40: L'administration est bien assurée par les utilisateurs. | I40: L'administration est-elle bien assurée par les utilisateurs? | J40: OUI | K40: Rapports de performance de l'application, tableau de bord de suivi des performances | L40: Droits d'accès mal attribués ou non limités | M40: Moyen | N40: Difficultés à utiliser l'application, manque d'autonomie des utilisateurs. | O40: Offrir des formations continues.
H41: Les droits d'accès sont correctement attribués et limités en fonction des besoins et des rôles des utilisateurs | I41: Les droits d'accès sont-ils correctement attribués et limités en fonction des besoins et des rôles des utilisateurs? | J41: OUI | K41: Rapports de suivi du respect du SLA, rapports de performance de l'application | L41: Absence de rapport mensuel sur les performances de l'application | M41: Élevé | N41: Accès non autorisés aux données sensibles, risques de fuites d'informations. | O41: Renforcer les contrôles d'accès.
G42: Vérifier qu’un mot de passe est associé à l'identifiant | H42: Le propriétaire dispose d'un compte rendu mensuel de la performance de l'application ; | I42: Le propriétaire dispose-t-il d'un compte rendu mensuel de la performance de l'application ? | J42: PAS | K42: Politiques de gestion des mots de passe, journaux d'activité du système | L42: Non-respect du contrat de service dans le rapport de performance | M42: Élevé | N42: Difficultés à évaluer les performances de l'application, manque de visibilité. | O42: Mettre en place des tableaux de bord.
H43: Le compte rendu respecte le contrat du service | I43: Le compte rendu respecte-t-il le contrat du service? | J43: PAS | K43: Politiques de sécurité, journaux d'activité du système | L43: Absence de politique de changement périodique des mots de passe | M43: Élevé | N43: Non-respect des engagements contractuels, litiges potentiels. | O43: Effectuer des audits réguliers.
H44: Changement périodique des mots de passe imposé par le système | I44: Y a-t-il un changement périodique des mots de passe imposé par le système? | J44: OUI | K44: Politiques de sécurité, rapports de tests de sécurité | L44: Non-implémentation d'un mécanisme de verrouillage après tentatives infructueuses | M44: Élevé | N44: Mots de passe faibles, risques de piratage. | O44: Imposer des politiques de mots de passe robustes.
H45: Mise en place d’un mécanisme de verrouillage après plusieurs tentatives échouées | I45: Est-il mis en place un mécanisme de verrouillage après plusieurs tentatives échouées? | J45: PAS | K45: Guides d'utilisation de l'application, manuels de formation | L45: Absence d'authentification multi-facteurs (MFA) pour les accès sensibles | M45: Élevé | N45: Accès non autorisés après plusieurs tentatives infructueuses, risques de piratage. | O45: Mettre en place des mécanismes de blocage.
H46: Activation de l’authentification multi-facteurs (MFA) pour les accès sensibles | I46: L'activation de l’authentification multi-facteurs (MFA) pour les accès sensibles est-il opérationnel? | J46: OUI | K46: Manuels de formation à l'application, listes de diffusion des manuels | L46: Absence de guide utilisateur/manuel de procédures | M46: Moyen | N46: Vulnérabilités liées à l'authentification, risques de piratage. | O46: Utiliser des méthodes d'authentification sécurisées.
G47: S’assurer que les tentatives de connexions infructueuses à l'application sont suivies | H47: Il existe un guide utilisateurs / manuel de procédures ; | I47: existe-t-il un guide utilisateurs / manuel de procédures ? | J47: PAS | K47: Manuels de formation à l'application, registres de mise à jour des manuels | L47: Manuel non diffusé | M47: Faible | N47: Difficultés à utiliser l'application, manque d'autonomie des utilisateurs. | O47: Offrir des formations et des ressources.
H48: Le manuel est diffusé ; | I48: Le manuel est-il diffusé ? | J48: PAS | K48: Manuels de formation, registres de compétences des utilisateurs | L48: Manuel obsolète | M48: Faible | N48: Diffusion restreinte du manuel, manque de transparence et d'accessibilité. | O48: Rendre les manuels accessibles à tous.
H49: Le manuel est à jour ; | I49: Le manuel est-il à jour ? | J49: PAS | K49: Manuels de formation, guides d'utilisation de l'application | L49: Manuel non maîtrisé | M49: Faible | N49: Informations obsolètes ou incorrectes, risques d'erreurs d'utilisation. | O49: Établir des processus de mise à jour.
H50: Le manuel est maitrisé ; | I50: Le manuel est-il maitrisé ? | J50: PAS | K50: Rapports de déploiement d'antivirus et d'anti-malware, rapports de mise à jour des signatures de virus | L50: Absence de mode d'emploi dans le manuel | M50: Faible | N50: Difficultés à comprendre le fonctionnement de l'application, manque d'efficacité. | O50: Créer des guides d'utilisation.
H51: Le manuel comprend le mode d’emploi de l'application ; | I51: Le manuel comprend-il le mode d’emploi de l'application ? | J51: PAS | K51: Rapports de mise à jour des signatures de virus, journaux d'activité du système | L51: Antivirus et anti-malware non déployés sur tous les postes et serveurs | M51: Faible | N51: Difficultés à résoudre les problèmes techniques, dépendance excessive du support informatique. | O51: Mettre en place une base de connaissances.
F52: Fonction informatique | G52: S’assurer que les tâches relatives au développement et à l'exploitation de l'application sont bien suivies et documentées ; | H52: Déploiement d’un antivirus et d’un anti-malware sur tous les postes et serveurs | I52: Y a-t-il eu le déploiement d’un antivirus et d’un anti-malware sur tous les postes et serveurs? | J52: PAS | K52: Rapports d'analyse de fichiers et de systèmes, journaux d'activité du système | L52: Bases de signatures de virus non mises à jour automatiquement et régulièrement | M52: Faible | N52: Vulnérabilités liées aux virus et malwares, risques de piratage et de perte de données. | O52: Mettre en place des logiciels antivirus et des mises à jour régulières.
H53: Mise à jour automatique et régulière des bases de signatures de virus | I53: La mise à jour automatique et régulière des bases de signatures de virus est-elle effectuée? | J53: PAS | K53: Supports de formation sur les risques liés aux malwares, registres de participation aux formations | L53: Analyse périodique des fichiers et systèmes pour détecter les menaces non effectuée | M53: Faible | N53: Vulnérabilités liées aux virus et malwares, risques de piratage et de perte de données. | O53: Organiser des sessions de formation et de sensibilisation pour les employés.
H54: Analyse périodique des fichiers et des systèmes pour détecter les menaces | I54: Ya t-il l'analyse périodique des fichiers et des systèmes pour détecter les menaces? | J54: PAS | K54: Politiques de restriction des droits d'installation de logiciels, journaux d'activité du système | L54: Formation et sensibilisation des utilisateurs aux risques liés aux malwares insuffisantes | M54: Faible | N54: Vulnérabilités liées aux virus et malwares, risques de piratage et de perte de données. | O54: Établir une politique stricte d'installation de logiciels.
H55: Formation et sensibilisation des utilisateurs aux risques liés aux malwares | I55: Ya t-il la formation et la sensibilisation des utilisateurs aux risques liés aux malwares? | J55: PAS | K55: Politiques de configuration du pare-feu, journaux d'activité du pare-feu | L55: Droits d'installation de logiciels non restreints aux administrateurs | M55: Faible | N55: Manque de sensibilisation aux risques liés aux malwares, vulnérabilités humaines. | O55: Utiliser des connexions sécurisées (VPN, chiffrement).
H56: Restriction des droits d’installation de logiciels aux administrateurs uniquement | I56: La restriction des droits d’installation de logiciels se fait-elle aux administrateurs uniquement? | J56: PAS | K56: Politiques de configuration du VPN, journaux d'activité du VPN | L56: Pare-feu filtrant les connexions entrantes et sortantes non mis en place | M56: Faible | N56: Installation de logiciels non autorisés, risques d'erreurs et de fraudes. | O56: Mettre en place des contrôles d'accès robustes pour les accès distants.
G57: S’assurer que l'accès aux bibliothèques de production est réglementé ; | H57: Mise en place d’un pare-feu filtrant les connexions entrantes et sortantes | I57: A-t-il été mis en place un pare-feu filtrant les connexions entrantes et sortantes? | J57: PAS | K57: Politiques de segmentation du réseau, schémas de segmentation du réseau | L57: Connexions distantes non sécurisées via VPN | M57: Faible | N57: Vulnérabilités liées aux connexions non sécurisées, risques de piratage. | O57: Segmenter le réseau pour limiter la propagation des attaques.
H58: Sécurisation des connexions via VPN pour les accès distants | I58: y a-t-il la sécurisation des connexions via VPN pour les accès distants? | J58: PAS | K58: Rapports de configuration de l'IDS/IPS, journaux d'activité de l'IDS/IPS | L58: Segmentation des réseaux pour limiter la propagation des attaques non mise en place | M58: Faible | N58: Vulnérabilités liées aux accès distants, risques de piratage. | O58: Installer des systèmes de détection d'intrusions (IDS) et des alertes.
H59: Segmentation des réseaux pour limiter la propagation des attaques | I59: La segmentation des réseaux pour limiter la propagation des attaques a-t-elle été effectuée? | J59: OUI | K59: Politiques de segmentation du réseau, schémas de segmentation du réseau | L59: Surveillance et détection des intrusions avec un IDS/IPS non mise en place | M59: Faible | N59: Propagation des attaques à travers le réseau, risques de paralysie des systèmes. | O59: Renforcer les contrôles d'accès réseau et les authentifications.
H60: Surveillance et détection des intrusions avec un IDS/IPS | I60: La surveillance et La détection des intrusions avec un IDS/IPS ont-t-elles été effectuées? | J60: OUI | K60: Rapports de configuration de l'IDS/IPS, journaux d'activité de l'IDS/IPS | L60: Règles strictes de gestion des accès réseau non définies et non appliquées | M60: Faible | N60: Difficultés à détecter les intrusions, manque de réactivité. | O60: Établir un plan de continuité des activités et de conformité.
H61: Définition et application de règles strictes de gestion des accès réseau | I61: La définition et l' application de règles strictes de gestion des accès réseau ont-t-elles été effectuées? | J61: OUI | K61: Politiques de gestion des accès réseau, journaux d'activité du réseau | L61: Risque en cas d'absence de Définition et application de règles strictes de gestion des accès réseau | M61: Faible | N61: Vulnérabilités liées aux accès réseau, risques de piratage. | O61: Mettre en place des sauvegardes régulières et des plans de récupération des données.
G62: Vérifier que la maintenance de la séparation des tâches est effective | H62: Existence d’une politique de sauvegarde documentée | I62: Existe-t-il une politique de sauvegarde documentée? | J62: OUI | K62: Politique de sauvegarde des données, rapports de sauvegarde | L62: Absence de politique de sauvegarde documentée | M62: Faible | N62: Pertes financières, interruption des activités, non-conformité réglementaire. | O62: Tester régulièrement les procédures de restauration des données.
H63: Réalisation de sauvegardes automatiques à intervalles réguliers | I63: La réalisation de sauvegardes automatiques à intervalles réguliers a-t-elle été effectuée? | J63: OUI | K63: Rapports de sauvegarde, procédures de sauvegarde automatique | L63: Sauvegardes automatiques non réalisées à intervalles réguliers | M63: Élevé | N63: Données irrécupérables en cas d’incident (cyberattaque, panne matérielle). | O63: Documenter et vérifier les processus de restauration.
H64: Stockage des sauvegardes sur des supports sécurisés et redondants | I64: Le stockage des sauvegardes se fait-il sur des supports sécurisés et redondants? | J64: OUI | K64: Politiques de stockage des sauvegardes, rapports de stockage des sauvegardes | L64: Stockage des sauvegardes sur des supports non sécurisés ou non redondants | M64: Élevé | N64: Impossibilité de restaurer les données après un sinistre (incendie, ransomware). | O64: Élaborer un plan de gestion des risques et de sauvegarde.
H65: Tests réguliers de restauration des données pour vérifier leur intégrité | I65: Des tests réguliers de restauration des données sont-ils effectués pour vérifier leur intégrité ? | J65: OUI | K65: Rapports de tests de restauration des données, procédures de restauration des données | L65: Tests de restauration des données non réalisés régulièrement | M65: Élevé | N65: Échec de la restauration en cas de besoin critique. | O65: Mettre en place des systèmes de sécurité physique et logique.
H66: Séparation des sauvegardes des systèmes de production pour éviter les attaques (ex. ransomware) | I66: Les sauvegardes sont-elles séparées des systèmes de production pour prévenir les attaques, notamment les ransomwares ? | J66: OUI | K66: Politiques de séparation des sauvegardes, procédures de sauvegarde | L66: Sauvegardes non séparées des systèmes de production | M66: Élevé | N66: Perte totale des données et paralysie de l’organisation. | O66: Renforcer la sécurité des locaux et des systèmes.
G67: S’assurer que l'équipe actuelle en charge de la maintenance est autonome et compétente ; | H67: Mise en place de contrôle d’accès physique (badge, biométrie, etc.) | I67: Un contrôle d’accès physique est-il mis en place (badge, biométrie, etc.) ? | J67: PAS | K67: Politiques de contrôle d'accès physique, rapports de contrôle d'accès physique | L67: Contrôle d'accès physique insuffisant | M67: Élevé | N67: Vol de données, destruction matérielle, interruption de service. | O67: Utiliser des outils de surveillance et de détection des anomalies.
H68: Surveillance des locaux avec des caméras et un système d’alarme | I68: Les locaux sont-ils surveillés par des caméras et un système d’alarme ? | J68: PAS | K68: Rapports de surveillance des locaux, procédures de surveillance des locaux | L68: Surveillance des locaux inadéquate (caméras, alarmes) | M68: Élevé | N68: Vol, vandalisme ou espionnage industriel. | O68: Établir des procédures claires d'enquête et de traçabilité.
H69: Restriction des accès aux seules personnes autorisées | I69: Les accès sont-ils restreints aux seules personnes autorisées ? | J69: PAS | K69: Politiques de restriction d'accès, journaux d'activité des locaux | L69: Accès non restreints aux personnes autorisées | M69: Moyen | N69: Fuite de données, manipulation frauduleuse des systèmes. | O69: Avoir des plans de continuité et de reprise d'activité.
H70: Enregistrement et suivi des entrées/sorties dans les zones sensibles | I70: Un enregistrement et un suivi des entrées/sorties dans les zones sensibles sont-ils effectués ? | J70: PAS | K70: Procédures d'enregistrement des entrées/sorties, journaux d'activité des zones sensibles | L70: Enregistrement et suivi des entrées/sorties inexistants | M70: Faible | N70: Difficulté à identifier les responsables en cas d’incident. | O70: Mettre en œuvre des politiques de conformité et de sensibilisation.
H71: Sécurisation des équipements critiques (serveurs, baies de stockage, etc.) contre les manipulations non autorisées | I71: Les équipements critiques (serveurs, baies de stockage, etc.) sont-ils sécurisés contre les manipulations non autorisées ? | J71: PAS | K71: Politiques de sécurisation des équipements critiques, rapports de sécurité des équipements | L71: Sécurisation des équipements critiques insuffisante | M71: Moyen | N71: Interruption de service, perte de données. | O71: Utiliser des outils de prévention et de détection des fuites de données.
G72: S’assurer de l’existence de procédure formalisée et standard de maintenance de l’application | H72: Signature d’un accord de confidentialité (NDA) avec les prestataires | I72: Un accord de confidentialité (NDA) est-il signé avec les prestataires ? | J72: PAS | K72: Accords de confidentialité (NDA) avec les prestataires, politiques de gestion des prestataires | L72: Accord de confidentialité (NDA) non signé avec les prestataires | M72: Élevé | N72: Atteinte à la réputation, sanctions légales. | O72: Effectuer des audits réguliers de sécurité et de performance.
H73: Attribution des accès selon le principe du moindre privilège | I73: Les accès sont-ils attribués selon le principe du moindre privilège ? | J73: PAS | K73: Politiques d'attribution des accès, journaux d'activité du système | L73: Accès non attribués selon le principe du moindre privilège | M73: Moyen | N73: Compromission des systèmes, exfiltration de données. | O73: Évaluer régulièrement la sécurité des fournisseurs et des partenaires.
H74: Surveillance des actions des prestataires sur les systèmes critiques | I74: Les actions des prestataires sur les systèmes critiques sont-elles surveillées ? | J74: PAS | K74: Rapports de surveillance des actions des prestataires, politiques de gestion des prestataires | L74: Surveillance des actions des prestataires insuffisante | M74: Moyen | N74: Dégradation du système, fuite de données. | O74: Mettre en place une authentification multi-facteurs.
H75: Vérification des politiques de sécurité des fournisseurs avant tout partenariat | I75: Les politiques de sécurité des fournisseurs sont-elles vérifiées avant tout partenariat ? | J75: OUI | K75: Rapports de vérification des politiques de sécurité des fournisseurs, politiques de gestion des fournisseurs | L75: Vérification des politiques de sécurité des fournisseurs inexistante | M75: Moyen | N75: Compromission du SI via une faille tierce. | O75: Élaborer des plans d'urgence et de communication de crise.
H76: Réalisation d’audits de sécurité périodiques sur les accès des tiers | I76: Des audits de sécurité périodiques sont-ils réalisés sur les accès des tiers ? | J76: OUI | K76: Rapports d'audits de sécurité des accès des tiers, politiques de gestion des tiers | L76: Audits de sécurité périodiques des accès des tiers non réalisés | M76: Moyen | N76: Utilisation frauduleuse de comptes tiers. | O76: Mettre en œuvre des solutions de sécurité réseau avancées.
F77: Adéquation de l'application aux bésoins | G77: Vérifier qu’un Schéma-directeur du système d’information existe et est à jour ; | H77: Existence d’un plan de réponse aux incidents documenté | I77: Un plan de réponse aux incidents est-il documenté et disponible ? | J77: OUI | K77: Plan de réponse aux incidents, procédures de gestion des incidents | L77: Plan de réponse aux incidents non documenté | M77: Élevé | N77: Aggravation de l’impact (pertes financières, atteinte à l’image). | O77: Avoir une stratégie de réponse rapide aux incidents de sécurité.
H78: Mise en place d’un centre opérationnel de sécurité (SOC) ou d’un mécanisme de monitoring | I78: Un centre opérationnel de sécurité (SOC) ou un mécanisme de monitoring est-il mis en place ? | J78: OUI | K78: Rapports de configuration du SOC ou du mécanisme de monitoring, journaux d'activité du SOC ou du mécanisme de monitoring | L78: Centre opérationnel de sécurité (SOC) ou mécanisme de monitoring non mis en place | M78: Élevé | N78: Propagation de l’attaque, exfiltration de données. | O78: Former une équipe de réponse aux incidents.
H79: Définition de procédures de déclaration et d’analyse des incidents | I79: Des procédures de déclaration et d’analyse des incidents sont-elles définies ? | J79: OUI | K79: Procédures de déclaration et d'analyse des incidents, rapports d'analyse des incidents | L79: Procédures de déclaration et d'analyse des incidents non définies | M79: Élevé | N79: Augmentation des dommages (ex. ransomware non contenu). | O79: Analyser les incidents pour éviter les répétitions.
H80: Tests réguliers des scénarios de réponse aux incidents | I80: Des tests réguliers des scénarios de réponse aux incidents sont-ils effectués ? | J80: OUI | K80: Rapports de tests des scénarios de réponse aux incidents, procédures de gestion des incidents | L80: Tests des scénarios de réponse aux incidents non réalisés | M80: Élevé | N80: Échec de la réponse, paralysie prolongée. | O80: Améliorer les processus et les outils de travail.
H81: Capitalisation des incidents passés pour améliorer la résilience du système | I81: Les incidents passés sont-ils analysés pour améliorer la résilience du système ? | J81: OUI | K81: Registres des incidents, rapports d'analyse des incidents | L81: Capitalisation des incidents passés inexistante | M81: Élevé | O81: Renforcer la culture de la sécurité au sein de l'organisation.
G82: Vérifier qu’un Schéma-directeur du système d’information existe et est à jour ; | H82: Mise en place d’indicateurs permettant de mesurer la contribution de l’application aux objectifs stratégiques | I82: Des indicateurs permettent-ils de mesurer la contribution de l’application aux objectifs stratégiques ? | J82: OUI | K82: Tableaux de bord des indicateurs de performance, rapports de suivi des objectifs stratégiques | L82: Indicateurs de contribution de l'application aux objectifs stratégiques non mis en place | M82: Élevé | N82: Pertes financières, interruption des activités, non-conformité réglementaire | O82: Mettre en place une gouvernance de projet solide.
G83: S’assurer que la définition des spécifications ou les critères de choix de la solution a été clairement établie ; | H83: Existence d’une documentation technique et fonctionnelle à jour | I83: Une documentation technique et fonctionnelle à jour existe-t-elle ? | J83: OUI | K83: Documentation technique et fonctionnelle de l'application, registres de mises à jour de la documentation | L83: Documentation technique et fonctionnelle non à jour | M83: Élevé | N83: Données irrécupérables en cas d'incident (cyberattaque, panne matérielle) | O83: Assurer la conformité et l'éthique dans toutes les opérations.
H84: Présence d’un processus de gestion des évolutions et des mises à jour | I84: Un processus de gestion des évolutions et des mises à jour est-il en place ? | J84: OUI | K84: Procédures de gestion des évolutions et des mises à jour, registres des changements de l'application | L84: Processus de gestion des évolutions et mises à jour inexistant | M84: Élevé | N84: Impossibilité de restaurer les données après un sinistre | O84: Former et sensibiliser le personnel sur la sécurité.
H85: Utilisation de technologies standards et pérennes pour garantir la maintenabilité | I85: Des technologies standards et pérennes sont-elles utilisées pour garantir la maintenabilité ? | J85: OUI | K85: Politiques d'utilisation de technologies standards et pérennes, rapports d'audit de la maintenabilité | L85: Technologies non standards ou non pérennes utilisées | M85: Élevé | N85: Échec de la restauration en cas de besoin critique | O85: Améliorer la qualité des services et la satisfaction client.
H86: Capacité d’adaptation de l’application aux changements réglementaires et technologiques | I86: L’application est-elle capable de s’adapter aux changements réglementaires et technologiques ? | J86: OUI | K86: Rapports d'évaluation de la capacité d'adaptation de l'application, plans de mise à jour de l'application | L86: Capacité d'adaptation de l'application aux changements réglementaires et technologiques insuffisante | M86: Élevé | N86: Perte totale des données et paralysie de l'organisation | O86: Planifier les migrations avec des analyses de coûts détaillées.
H87: Disponibilité d’une équipe ou d’un prestataire en charge de la maintenance corrective et évolutive | I87: Une équipe ou un prestataire est-il chargé de la maintenance corrective et évolutive ? | J87: OUI | K87: Contrats de maintenance avec l'équipe ou le prestataire, rapports d'activité de la maintenance | L87: Équipe ou prestataire en charge de la maintenance corrective et évolutive indisponible | M87: Élevé | N87: Vol de données, destruction matérielle, interruption de service | O87: Effectuer des évaluations de sécurité régulières.
G88: Vérifier que les tâches des utilisateurs dans l’application sont clairement définies ; | H88: Définition d’objectifs de performance clairs et mesurables (temps de réponse, disponibilité, etc.) | I88: Des objectifs de performance clairs et mesurables (temps de réponse, disponibilité, etc.) sont-ils définis ? | J88: OUI | K88: Tableaux de bord des indicateurs de performance, rapports de suivi des objectifs de performance | L88: Objectifs de performance non définis ou non mesurables | M88: Élevé | N88: Vol, vandalisme ou espionnage industriel | O88: Établir une politique de conformité et de suivi rigoureux.
H89: Mise en place de tests de performance réguliers et analyse des résultats | I89: Des tests de performance réguliers sont-ils réalisés et leurs résultats analysés ? | J89: OUI | K89: Rapports de tests de performance, tableaux de bord des indicateurs de performance | L89: Tests de performance réguliers non réalisés | M89: Moyen | N89: Fuite de données, manipulation frauduleuse | O89: Maintenir la conformité avec les normes et règlements.
H90: Surveillance en temps réel des indicateurs de performance | I90: Une surveillance en temps réel des indicateurs de performance est-elle mise en place ? | J90: OUI | K90: Tableaux de bord des indicateurs de performance en temps réel, rapports d'analyse de l'utilisation des ressources | L90: Surveillance en temps réel des indicateurs de performance inexistante | M90: Moyen | N90: Difficulté à identifier les responsables | O90: Prévoir des audits réguliers et des mises à jour de conformité.
H91: Optimisation des ressources pour assurer un fonctionnement fluide sous charge élevée | I91: Les ressources sont-elles optimisées pour assurer un fonctionnement fluide sous charge élevée ? | J91: OUI | K91: Plans d'amélioration continue des performances, rapports d'analyse des performances | L91: Optimisation des ressources insuffisante sous charge élevée | M91: Moyen | N91: Interruption de service, perte de données | O91: Mettre en place des mesures préventives et réactives.
H92: Existence d’un plan d’amélioration continue des performances en cas de dégradation | I92: Un plan d’amélioration continue des performances est-il prévu en cas de dégradation ? | J92: OUI | K92: Rapports d'analyse des risques, plans de traitement des risques | L92: Plan d'amélioration continue des performances inexistant | M92: Moyen | N92: Atteinte à la réputation, sanctions légales | O92: Préparer les systèmes pour les audits et les contrôles.
G93: Vérifier que des systèmes parallèles sont maintenus en activité ; | H93: Réalisation d’une analyse des risques associés à l’application | I93: Une analyse des risques associés à l’application est-elle régulièrement réalisée ? | J93: OUI | K93: Plans de traitement des risques, rapports de suivi des mesures de mitigation | L93: Analyse des risques associés à l'application non réalisée | M93: Élevé | N93: Compromission des systèmes, exfiltration | O93: Renforcer l'infrastructure et effectuer des mises à jour régulières.
H94: Identification et mise en œuvre de mesures de mitigation adaptées | I94: L’identification et la mise en œuvre de mesures de mitigation adaptées sont-elles effectuées ? | J94: OUI | K94: Rapports d'évaluation des risques mis à jour, plans de mise à jour de l'évaluation des risques | L94: Identification et mise en œuvre de mesures de mitigation insuffisantes | M94: Élevé | N94: Dégradation du système, fuite de données | O94: Avoir des procédures d'urgence et de continuité.
H95: Mise à jour régulière de l’évaluation des risques en fonction des évolutions du SI | I95: L’évaluation des risques est-elle mise à jour régulièrement en fonction des évolutions du SI ? | J95: OUI | K95: Plans de gestion de crise, procédures de gestion de crise | L95: Évaluation des risques non mise à jour régulièrement | M95: Élevé | N95: Compromission via une faille tierce | O95: Mettre en place des systèmes de monitoring et de reporting.
H96: Existence d’un plan de gestion de crise en cas de faille majeure | I96: Un plan de gestion de crise existe-t-il en cas de faille majeure ? | J96: OUI | K96: Supports de formation sur les risques liés à l'application, registres de participation aux formations | L96: Plan de gestion de crise inexistant en cas de faille majeure | M96: Élevé | N96: Utilisation frauduleuse de comptes tiers | O96: Optimiser les processus de travail et de communication.
H97: Sensibilisation des utilisateurs et formation aux risques liés à l’application | I97: Les utilisateurs sont-ils sensibilisés et formés aux risques liés à l’application ? | J97: OUI | K97: Politiques de chiffrement des données, rapports de tests de chiffrement | L97: Sensibilisation et formation des utilisateurs aux risques insuffisantes | M97: Élevé | N97: Aggravation de l'impact (pertes, image) | O97: Élaborer des plans de réponse rapide aux incidents.
F98: Performance et de la Rentabilité | G98: Vérifier qu’une évaluation de la rentabilité existe | H98: Implémentation de mécanismes de chiffrement des données sensibles | I98: Des mécanismes de chiffrement des données sensibles sont-ils implémentés ? | J98: OUI | K98: Politiques de restriction d'accès aux données, journaux d'activité du système | L98: Chiffrement des données sensibles non implémenté | M98: Élevé | N98: Propagation de l'attaque, exfiltration | O98: Tester régulièrement les procédures de reprise.
H99: Restriction des accès aux données en fonction des profils utilisateurs | I99: Les accès aux données sont-ils restreints en fonction des profils utilisateurs ? | J99: OUI | K99: Politiques de conservation et de suppression des données, rapports de gestion des données | L99: Accès aux données non restreints selon les profils utilisateurs | M99: Moyen | N99: Augmentation des dommages | O99: Former les équipes à la gestion de crise et à la communication.
H100: Mise en place de politiques de conservation et de suppression des données | I100: Des politiques de conservation et de suppression des données sont-elles mises en place ? | J100: OUI | K100: Rapports d'audits de sécurité, plans d'action suite aux audits | L100: Politiques de conservation et de suppression des données non mises en place | M100: Moyen | N100: Échec de la réponse, paralysie | O100: Avoir des plans de continuité pour les services essentiels.
...

Sheet 4.2
A1: Domaines | B1: Points de Contrôle | C1: Objectifs de contrôle | D1: Critères d’évaluation | E1: Question d’Évaluation | F1: Réponses | G1: Documents Requis | H1: Risques | I1: Criticité | J1: Conséquences | K1: Recommandations
A2: FONCTION INFORMATIQUE | B2: Rôle et positionnement de l'informatique dans l'organisation | C2: Vérifier qu’ont été créés des Comités « informatique » (stratégique, pilotage,..) regroupant les différentes directions de l’Organisation en charge de recenser les besoins et les opportunités, gérer les priorités et suivre les projets | D2: Présence d’un Comité Informatique | E2: Le Comité Informatique est-il formellement mis en place ? | F2: NON | G2: Procès-verbal de création du comité, Charte de fonctionnement | H2: Manque de pilotage stratégique du SI | I2: Elevée | J2: Investissements non alignés avec les objectifs. | K2: Élaborer un plan stratégique SI en concertation avec les métiers.
D3: Fréquence des réunions | E3: Les réunions du Comité Informatique se tiennent-elles régulièrement ? | F3: OUI | G3: Calendrier annuel des réunions, Archives des comptes-rendus | H3: Perte de réactivité dans la prise de décision | I3: Moyenne | J3: Opportunités manquées et perte d'avantage concurrentiel. | K3: Mettre en place un processus de décision agile et transparent.
D4: Documentation des décisions | E4: Les décisions prises lors des réunions sont-elles systématiquement documentées ? | F4: PAS | G4: Registre des décisions, Comptes-rendus signés | H4: Absence de traçabilité des décisions | I4: Faible | J4: Difficulté à justifier les choix et à tirer des leçons des erreurs. | K4: Documenter systématiquement les décisions et les justifications.
D5: Mécanismes de suivi des projets | E5: Des mécanismes de suivi des projets informatiques sont-ils en place ? | F5: OUI | G5: Dashboard de suivi, Rapports d'avancement mensuels | H5: Dérive des délais, des coûts ou de la qualité | I5: Moyenne | J5: Dépassements budgétaires et insatisfaction des utilisateurs. | K5: Mettre en place un suivi rigoureux des projets et des indicateurs de performance.
D6: Implication des directions métiers | E6: Les directions métiers sont-elles impliquées dans les projets informatiques ? | F6: NON | G6: PV de réunions métiers, Lettres de mission des sponsors | H6: Solutions SI inadaptées aux besoins métiers | I6: Faible | J6: Faible adoption des outils et perte de productivité. | K6: Impliquer les utilisateurs métiers dès la conception des solutions.
C7: Vérifier l’existence d’une charte informatique ou de tout autre document définissant le rôle et le périmètre de responsabilité de la DSI | D7: Existence d’un document formalisé | E7: Un document formalisé sur la gouvernance SI existe-t-il ? | F7: OUI | G7: Politique de gouvernance SI, Procédure de validation | H7: Incohérences ou flou organisationnel | I7: Elevée | J7: Doublons de tâches et perte d'efficacité. | K7: Clarifier les rôles et responsabilités de chacun.
D8: Clarté des rôles de la DSI | E8: Les rôles et responsabilités de la DSI sont-ils clairement définis ? | F8: OUI | G8: Organigramme fonctionnel, Fiches de poste | H8: Conflits ou doublons de responsabilités | I8: Moyenne | J8: Tension et retards dans les projets. | K8: Définir les responsabilités et mettre en place des instances de coordination.
D9: Validation par la direction | E9: Ce document a-t-il été validé par la direction générale ? | F9: OUI | G9: PV de validation COMEX, Notes de validation officielles | H9: Projets validés sans alignement stratégique | I9: Faible | J9: Gaspillage de ressources et manque de valeur ajoutée. | K9: Évaluer systématiquement l'alignement stratégique des projets.
D10: Communication du document | E10: Le document de gouvernance est-il communiqué à l’ensemble des parties concernées ? | F10: OUI | G10: Plan de diffusion, Accusés de réception | H10: Incompréhension des orientations SI | I10: Moyenne | J10: Résistance au changement et difficultés de mise en œuvre. | K10: Communiquer clairement les orientations SI et impliquer les équipes.
D11: Mise à jour régulière | E11: Ce document est-il mis à jour régulièrement ? | F11: OUI | G11: Journal des modifications, Historique des versions | H11: Obsolescence des règles suivies | I11: Faible | J11: Non-conformité et vulnérabilités de sécurité. | K11: Mettre en place une veille réglementaire et technologique.
C12: Évaluer le degré d’implication et de maîtrise des organes de gestion dans les systèmes d’information de l’Organisation | D12: Niveau de participation des dirigeants | E12: Les dirigeants participent-ils activement à la gouvernance des systèmes d'information ? | F12: PAS | G12: Listes de présence aux réunions, PV de décisions stratégiques | H12: Perte de légitimité du SI | I12: Elevée | J12: Difficulté à obtenir des budgets et à mener des projets. | K12: Démontrer la valeur ajoutée du SI à travers des projets concrets.
D13: Connaissance des enjeux des SI | E13: Les enjeux liés aux SI sont-ils bien connus par les dirigeants ? | F13: OUI | G13: Présentations stratégiques, Comptes-rendus de briefings | H13: Décisions inadaptées aux réalités techniques | I13: Moyenne | J13: Projets irréalistes et échecs techniques. | K13: Impliquer les experts techniques dans les décisions stratégiques.
D14: Utilisation des outils SI par la direction | E14: Les outils SI sont-ils effectivement utilisés par la direction ? | F14: OUI | G14: Logs d'accès, Rapports d'utilisation | H14: Frein à l’adoption des outils SI | I14: Elevée | J14: Sous-utilisation des outils et manque de retour sur investissement. | K14: Mettre en place un accompagnement au changement et une formation adaptée.
D15: Suivi des indicateurs de performance | E15: Les indicateurs de performance SI sont-ils suivis de manière régulière ? | F15: OUI | G15: Tableaux de bord, Rapports d'analyse trimestriels | H15: Absence d’alerte sur les dérives | I15: Elevée | J15: Problèmes non résolus et pertes financières. | K15: Mettre en place un système d'alerte et de reporting.
D16: Feedback sur la gouvernance des SI | E16: La gouvernance des SI fait-elle l’objet d’un retour d’expérience ou d’un feedback structuré ? | F16: OUI | G16: Enquêtes de satisfaction, Rapports d'audit | H16: Gouvernance inefficace | I16: Moyenne | J16: Manque de pilotage et décisions incohérentes. | K16: Définir les rôles et responsabilités de la gouvernance.
C17: Vérifier en pratique que le leadership des grands projets est assuré par les organes de gestion | D17: Nomination d’un sponsor de projet | E17: Un sponsor de projet est-il systématiquement nommé pour chaque projet SI ? | F17: PAS | G17: Désignation officielle, PV de lancement | H17: Manque de leadership sur les projets | I17: Moyenne | J17: Projets qui s'éternisent et n'atteignent pas leurs objectifs. | K17: Désigner des chefs de projet compétents et leur donner les moyens de réussir.
D18: Suivi actif des projets par la direction | E18: La direction suit-elle activement l’avancement des projets ? | F18: OUI | G18: Rapports de comité de pilotage, Plans d'actions | H18: Perte d’alignement avec la stratégie | I18: Elevée | J18: Actions SI qui ne contribuent pas aux objectifs de l'entreprise. | K18: Mettre en place des indicateurs de suivi de l'alignement stratégique.
D19: Prise de décision stratégique | E19: La direction prend-elle des décisions stratégiques en lien avec les SI ? | F19: OUI | G19: PV de COMEX, Feuilles de décision | H19: Immobilisme ou actions incohérentes | I19: Elevée | J19: Perte de compétitivité et opportunités manquées. | K19: Favoriser l'innovation et l'agilité.
D20: Projets alignés avec la stratégie de l’organisation | E20: Les projets sont-ils bien alignés avec la stratégie globale de l’organisation ? | F20: OUI | G20: Cartographie des projets, Business cases | H20: Investissements sans valeur ajoutée | I20: Faible | J20: Gaspillage de ressources et manque de retour sur investissement. | K20: Évaluer systématiquement la valeur ajoutée des investissements SI.
D21: Ressources allouées adéquatement | E21: Les ressources nécessaires aux projets sont-elles allouées de manière adéquate ? | F21: OUI | G21: Budgets approuvés, Plans de charge | H21: Échec des projets par manque de moyens | I21: Faible | J21: Démotivation des équipes et perte de confiance. | K21: Allouer les ressources nécessaires aux projets et s'assurer de leur disponibilité.
C22: Vérifier que les métiers assurent leur rôle de MOA | D22: Désignation d’un responsable MOA | E22: Un responsable MOA est-il désigné pour piloter les projets métiers ? | F22: OUI | G22: Fiche de rôle MOA, PV de nomination | H22: Défaut de coordination métier-technique | I22: Elevée | J22: Solutions SI qui ne répondent pas aux besoins des utilisateurs. | K22: Mettre en place des instances de coordination entre les métiers et la DSI.
D23: Implication dans la définition des besoins | E23: Les directions métiers participent-elles à la définition des besoins ? | F23: NON | G23: Cahiers des charges, PV d'ateliers métiers | H23: Outils partiellement adaptés | I23: Moyenne | J23: Insatisfaction des utilisateurs et perte de productivité. | K23: Adapter les outils aux besoins spécifiques des utilisateurs.
D24: Validation des livrables | E24: Les livrables des projets sont-ils validés par les utilisateurs métiers ? | F24: NON | G24: Procès-verbaux de recette, Checklists de validation | H24: Mise en production non conforme | I24: Moyenne | J24: Incident de production et interruption de service. | K24: Mettre en place un processus de mise en production rigoureux.
D25: Formation des équipes métiers | E25: Les équipes métiers bénéficient-elles de formations adaptées aux solutions SI déployées ? | F25: NON | G25: Plans de formation, Évaluations post-formation | H25: Erreurs ou abandon des outils | I25: Moyenne | J25: Perte de données et retards dans les projets. | K25: Mettre en place des tests utilisateurs et un support technique efficace.
D26: Suivi de la satisfaction des utilisateurs | E26: La satisfaction des utilisateurs est-elle régulièrement mesurée et suivie ? | F26: OUI | G26: Enquêtes utilisateurs, Rapports de feedback | H26: Désengagement des utilisateurs | I26: Moyenne | J26: Faible adoption des outils et manque de retour sur investissement. | K26: Impliquer les utilisateurs dans le choix et la conception des outils.
B27: Planification stratégique | C27: Vérifier la couverture du périmètre fonctionnel | D27: Exhaustivité des fonctions couvertes | E27: L’ensemble des fonctions métiers est-il couvert par les solutions informatiques ? | F27: OUI | G27: PV de revues, Matrices RACI | H27: Solutions incomplètes | I27: Moyenne | J27: Insatisfaction des utilisateurs et manque de productivité. | K27: Définir les fonctionnalités attendues et s'assurer de leur réalisation.
D28: Validation des parties prenantes sur la couverture | E28: Les parties prenantes ont-elles validé la couverture fonctionnelle des systèmes ? | F28: OUI | G28: Études d'adéquation, Rapports d'analyse | H28: Blocages liés à des besoins non validés | I28: Moyenne | J28: Retards dans les projets et insatisfaction des utilisateurs. | K28: Mettre en place un processus de validation des besoins.
D29: Alignement avec les besoins métiers | E29: Les solutions mises en œuvre sont-elles bien alignées avec les besoins métiers ? | F29: OUI | G29: Registre des écarts, Plans de correction | H29: Retour sur investissement faible | I29: Moyenne | J29: Difficulté à justifier les investissements SI. | K29: Mettre en place un suivi du retour sur investissement des projets.
D30: Documentation des écarts éventuels | E30: Les écarts fonctionnels sont-ils documentés de manière formelle ? | F30: OUI | G30: Historique des mises à jour, Demandes de changement | H30: Non-identification des points critiques | I30: Elevée | J30: Problèmes non résolus et pertes financières. | K30: Mettre en place une analyse des risques et des points critiques.
D31: Mise à jour régulière selon les évolutions des besoins | E31: Les besoins sont-ils mis à jour régulièrement en fonction de leur évolution ? | F31: OUI | G31: Journal des modifications, Notes de version | H31: Outils mal alignés aux besoins actuels | I31: Elevée | J31: Perte de productivité et insatisfaction des utilisateurs. | K31: Adapter les outils aux besoins spécifiques des utilisateurs.
C32: Vérifier l’existence d’une analyse à jour des procédures de pilotage et de mise à jour du plan informatique | D32: Date de la dernière mise à jour | E32: La dernière mise à jour des besoins est-elle récente ? | F32: OUI | G32: Manuel des procédures, Guides opérationnels | H32: Utilisation de documents dépassés | I32: Elevée | J32: Erreurs et manque de productivité. | K32: Mettre en place une gestion documentaire efficace.
D33: Implication des parties prenantes dans l’analyse | E33: Les parties prenantes sont-elles impliquées dans l’analyse des besoins ? | F33: PAS | G33: Plans d'action, Rapports de suivi | H33: Sous-estimation des attentes réelles | I33: Elevée | J33: Solutions SI qui ne répondent pas aux besoins des utilisateurs. | K33: Impliquer les utilisateurs dans la définition des besoins.
D34: Formalisation des procédures documentées | E34: Les procédures de mise à jour sont-elles formalisées et documentées ? | F34: PAS | G34: Études d'impact, Mesures de performance | H34: Manque d'uniformité entraîne des erreurs. | I34: Elevée | J34: Données incohérentes et analyses erronées. | K34: Mettre en place des normes et des processus standardisés.
D35: Suivi de la mise en œuvre des actions identifiées | E35: Les actions identifiées lors de l’analyse sont-elles effectivement mises en œuvre et suivies ? | F35: PAS | G35: Registre de conformité, PV d'audits | H35: Retards compromettent les objectifs. | I35: Moyenne | J35: Manque de réactivité et opportunités manquées. | K35: Mettre en place une gestion de projet agile.
D36: Impact des mises à jour sur l’efficacité des processus | E36: Les documents sont-ils mis à jour conformément aux normes en vigueur ? | F36: PAS | G36: Inventaire des documents, Politique d'accès | H36: Mises à jour perturbent les opérations. | I36: Elevée | J36: Interruption de service et perte de productivité. | K36: Mettre en place un processus de mise à jour rigoureux.
C37: Vérifier l’existence des documents à jour d’urbanisme de l’Organisation | D37: Mise à jour des documents selon les normes en vigueur | E37: Les documents sont-ils accessibles aux parties prenantes concernées ? | F37: PAS | G37: Cartographie applicative, Schémas directeurs | H37: Non-conformité cause des sanctions. | I37: Elevée | J37: Amendes et perte de réputation. | K37: Mettre en place une veille réglementaire et un audit de conformité.
D38: Accessibilité des documents pour les parties prenantes | E38: Les documents sont-ils cohérents avec la stratégie d'urbanisme de l’organisation ? | F38: PAS | G38: PV de formations, Enquêtes d'adhésion | H38: Accès difficile freine la collaboration. | I38: Elevée | J38: Difficulté à justifier les choix et à tirer des leçons des erreurs. | K38: Documenter systématiquement les décisions et les justifications.
D39: Cohérence des documents avec la stratégie d'urbanisme | E39: Les équipes concernées se sont-elles approprié les documents d’urbanisme ? | F39: PAS | G39: Plans de revue, Feuilles de route | H39: Désalignement mène à des actions contradictoires. | I39: Moyenne | J39: Données incohérentes et analyses erronées. | K39: Mettre en place des normes et des processus standardisés.
D40: Appropriation des documents par les équipes concernées | E40: Les documents sont-ils révisés régulièrement en fonction des évolutions de l’organisation ? | F40: PAS | G40: Rapports d'analyse, Synthèses stratégiques | H40: Résistance limite l'efficacité. | I40: Elevée | J40: Dépassements budgétaires et insatisfaction des utilisateurs. | K40: Mettre en place un suivi rigoureux des projets et des indicateurs de performance.
D41: Révision régulière en fonction des évolutions de l’organisation | E41: Les analyses sont-elles actualisées de manière régulière ? | F41: PAS | G41: Tableaux de suivi, Bilans post-projet | H41: Documents obsolètes ne reflètent plus la réalité. | I41: Elevée | J41: Données obsolètes mènent à des erreurs. | K41: Mettre en place une veille réglementaire et technologique.
C42: Vérifier l’existence d’une analyse à jour des procédures de pilotage et de mise à jour du plan d’occupation des sols (POS | D42: Actualisation régulière des analyses | E42: Les recommandations issues des analyses sont-elles suivies et mises en œuvre ? | F42: PAS | G42: Plans de revue technique, Rapports d'analyse comparative | H42: Données obsolètes mènent à des erreurs. | I42: Moyenne | J42: Erreurs et manque de productivité. | K42: Mettre en place une gestion documentaire efficace.
D43: Suivi des recommandations mises en œuvre | E43: Les documents respectent-ils les normes locales en vigueur ? | F43: OUI | G43: Tableaux de suivi des recommandations, Bilans d'implémentation | H43: Recommandations non appliquées manquent des améliorations. | I43: Elevée | J43: Faible adoption des outils et perte de productivité. | K43: Impliquer les utilisateurs métiers dès la conception des solutions.
D44: Vérification de la conformité aux normes locales | E44: Les processus de mise à jour des documents sont-ils bien documentés ? | F44: PAS | G44: Checklists de conformité, Rapports d'audit réglementaire | H44: Non-respect cause des problèmes légaux. | I44: Elevée | J44: Gaspillage de ressources et manque de valeur ajoutée. | K44: Évaluer systématiquement l'alignement stratégique des projets.
D45: Documentation des processus de mise à jour | E45: Les parties prenantes sont-elles impliquées dans la révision du plan d’occupation des sols (POS) ? | F45: PAS | G45: Manuels de procédures de mise à jour, Historiques des modifications | H45: Manque de transparence complique la maintenance. | I45: Elevée | J45: Manque de pilotage et décisions incohérentes. | K45: Définir les rôles et responsabilités de la gouvernance.
D46: Implication des parties prenantes dans la révision du POS | E46: Les technologies actuelles sont-elles évaluées par rapport aux besoins de l’organisation ? | F46: PAS | G46: PV de réunions de révision, Enquêtes auprès des parties prenantes | H46: Besoins non pris en compte mènent à un plan inadapté. | I46: Faible | J46: Manque de réactivité et opportunités manquées. | K46: Mettre en place une gestion de projet agile.
C47: Vérifier la cohérence et l’homogénéité des technologies | D47: Évaluation des technologies actuelles par rapport aux besoins | E47: Les standards et meilleures pratiques sont-ils vérifiés et appliqués ? | F47: PAS | G47: Audits technologiques, Études de besoins fonctionnels | H47: Mauvaise utilisation entraîne des coûts inutiles. | I47: Elevée | J47: Manque de vision limite la planification. | K47: Élaborer un plan stratégique SI en concertation avec les métiers.
D48: Vérification des standards et des meilleures pratiques | E48: Les technologies sont-elles mises à jour régulièrement en fonction des évolutions technologiques ? | F48: PAS | G48: Référentiels de standards, Benchmarking sectoriel | H48: Non-adoption limite la compétitivité. | I48: Moyenne | J48: Problèmes non résolus et pertes financières. | K48: Mettre en place un système d'alerte et de reporting.
D49: Mise à jour régulière des technologies en fonction des évolutions | E49: Les technologies utilisées sont-elles alignées avec les objectifs stratégiques de l’organisation ? | F49: PAS | G49: Feuilles de route technologique, Plans de migration | H49: Obsolescence rend les systèmes vulnérables. | I49: Elevée | J49: Projets irréalistes et échecs techniques. | K49: Impliquer les experts techniques dans les décisions stratégiques.
D50: Alignement des technologies avec les objectifs stratégiques | E50: Les choix technologiques sont-ils adaptés aux ressources disponibles ? | F50: PAS | G50: Cartographies d'alignement stratégique, Business cases technologiques | H50: Technologies non-pertinentes ne soutiennent pas les objectifs. | I50: Moyenne | J50: Retards compromettent les objectifs. | K50: Mettre en place une gestion de projet agile.
D51: Adéquation des choix technologiques avec les ressources disponibles | E51: Les référentiels sont-ils uniques et précis ? | F51: PAS | G51: Études de faisabilité technique, Analyses de ressources | H51: Dépassement budgétaire ou manque de compétences. | I51: Elevée | J51: Solutions SI qui ne répondent pas aux besoins des utilisateurs. | K51: Mettre en place des instances de coordination entre les métiers et la DSI.
C52: Vérifier l’existence et l’unicité des référentiels (clients, fournisseurs, articles…) et des saisies | D52: Unicité et précision des référentiels | E52: Les référentiels sont-ils mis à jour en fonction des besoins ? | F52: OUI | G52: Référentiels unifiés, Dictionnaires de données | H52: Données erronées mènent à des décisions incorrectes. | I52: Faible | J52: Sous-utilisation des outils et manque de retour sur investissement. | K52: Mettre en place un accompagnement au changement et une formation adaptée.
D53: Mise à jour des référentiels selon les besoins | E53: Les référentiels sont-ils accessibles de manière centralisée et sécurisée ? | F53: OUI | G53: Plans de maintenance des référentiels, Demandes d'évolution | H53: Référentiels obsolètes ne reflètent pas la réalité. | I53: Elevée | J53: Tension et retards dans les projets. | K53: Définir les responsabilités et mettre en place des instances de coordination.
D54: Accès centralisé et sécurisé aux référentiels | E54: Les données saisies dans les référentiels sont-elles consistantes ? | F54: PAS | G54: Politiques d'accès aux référentiels, Logs de consultation | H54: Fuites compromettent la sécurité. | I54: Moyenne | J54: Amendes et perte de réputation. | K54: Mettre en place une veille réglementaire et un audit de conformité.
D55: Consistance des données saisies dans les référentiels | E55: Des processus de validation et de contrôle des référentiels sont-ils en place ? | F55: PAS | G55: Procédures de qualité des données, Rapports de cohérence | H55: Données incohérentes rendent les analyses peu fiables. | I55: Faible | J55: Erreurs et manque de productivité. | K55: Mettre en place une gestion documentaire efficace.
D56: Processus de validation et de contrôle des référentiels | E56: Des procédures clairement définies existent-elles pour la gestion des processus ? | F56: OUI | G56: Workflows de validation, Matrices de contrôle | H56: Manque de contrôle cause des erreurs. | I56: Elevée | J56: Insatisfaction des utilisateurs et manque de productivité. | K56: Définir les fonctionnalités attendues et s'assurer de leur réalisation.
B57: Budgets et coûts informatiques | C57: Évaluer l’organisation et les processus existants | D57: Existence de procédures clairement définies | E57: Les processus sont-ils adéquats par rapport aux objectifs de l’organisation ? | F57: PAS | G57: Manuels de procédures opérationnelles, Arbres décisionnels | H57: Interprétations divergentes causent des applications non-uniformes. | I57: Elevée | J57: Perte de compétitivité et opportunités manquées. | K57: Favoriser l'innovation et l'agilité.
D58: Adéquation des processus avec les objectifs de l’organisation | E58: Les processus sont-ils efficaces pour atteindre les objectifs fixés ? | F58: OUI | G58: Matrices d'adéquation processus/objectifs, Cartographies métiers | H58: Processus inefficaces n'atteignent pas les objectifs. | I58: Elevée | J58: Perte de données et retards dans les projets. | K58: Mettre en place des tests utilisateurs et un support technique efficace.
D59: Efficacité des processus dans l’atteinte des objectifs | E59: Les points de blocage dans l’organisation sont-ils identifiés et analysés ? | F59: PAS | G59: Indicateurs d'efficience, Rapports de performance processus | H59: Processus lents freinent la productivité. | I59: Faible | J59: Perte de productivité et insatisfaction des utilisateurs. | K59: Adapter les outils aux besoins spécifiques des utilisateurs.
D60: Identification des points de blocage dans l’organisation | E60: Un système de suivi des processus est-il en place pour favoriser l’amélioration continue ? | F60: PAS | G60: Registres des points bloquants, Analyses des goulots d'étranglement | H60: Non-résolution perpétue les inefficacités. | I60: Elevée | J60: Projets qui s'éternisent et n'atteignent pas leurs objectifs. | K60: Désigner des chefs de projet compétents et leur donner les moyens de réussir.
D61: Mise en place d’un suivi des processus pour les améliorations continues | E61: Les rapports de performance contiennent-ils les ratios clés nécessaires à l’analyse ? | F61: PAS | G61: Tableaux de bord d'amélioration continue, Plans d'optimisation | H61: Manque de suivi manque des optimisations. | I61: Faible | J61: Référentiels obsolètes ne reflètent pas la réalité. | K61: Mettre en place une gestion documentaire efficace.
C62: Vérifier l’existence des ratios et des éléments de benchmark (interne et/ou externe, ratio coûts/CA, … | D62: Présence des ratios clés dans les rapports de performance | E62: Les performances sont-elles comparées à des benchmarks internes et externes ? | F62: PAS | G62: Reporting de management, Analyses des ratios clés | H62: Manque d'indicateurs rend les rapports peu informatifs. | I62: Elevée | J62: Solutions SI qui ne répondent pas aux besoins des utilisateurs. | K62: Impliquer les utilisateurs dans la définition des besoins.
D63: Comparaison avec des benchmarks internes et externes | E63: Les indicateurs choisis sont-ils pertinents pour évaluer la performance ? | F63: PAS | G63: Études comparatives sectorielles, Benchmarks historiques | H63: Manque de données comparatives limite l'évaluation. | I63: Elevée | J63: Tableau de bord inexistant empêche une vision globale. | K63: Mettre en place un tableau de bord consolidé pour la performance de la DSI.
D64: Pertinence des indicateurs choisis | E64: Les ratios sont-ils utilisés pour appuyer les décisions stratégiques ? | F64: PAS | G64: Grilles d'évaluation d'indicateurs, Matrices de pertinence | H64: Indicateurs non-alignés ne reflètent pas les performances. | I64: Moyenne | J64: Tableau de bord non utilisé limite la prise de décision. | K64: Utiliser le tableau de bord pour la prise de décision stratégique et opérationnelle.
D65: Utilisation des ratios pour la prise de décision stratégique | E65: Les données de benchmark sont-elles mises à jour régulièrement ? | F65: PAS | G65: Supports décisionnels, Analyses d'impact stratégique | H65: Interprétations erronées mènent à des décisions incorrectes. | I65: Elevée | J65: Utilisation de documents dépassés entraîne des erreurs. | K65: Mettre en place une gestion documentaire efficace.
D66: Mise à jour régulière des données de benchmark | E66: Des objectifs de court, moyen et long termes sont-ils assignés à la DSI ? | F66: PAS | G66: Feuille de route stratégique DSI, PV d'alignement stratégique | H66: Données obsolètes rendent les comparaisons inexactes. | I66: Moyenne | J66: Données obsolètes rendent les comparaisons inexactes. | K66: Mettre à jour régulièrement les données de benchmark.
B67: Mesure et suivi de la performance informatique | C67: Vérifier que des objectifs de court, moyen et long termes existent et sont assignés à la DSI (approche BSC ?) et que ces objectifs sont déclinés au sein de l’entité | D67: Existence d'objectifs de court, moyen et long termes assignés à la DSI | E67: Ces objectifs sont-ils alignés avec la stratégie globale de l’organisation ? | F67: PAS | G67: Cartographie d'alignement DSI/organisation, Référentiel d'objectifs | H67: Manque de vision limite la planification. | I67: Faible | J67: Manque de vision limite la planification. | K67: Établir des objectifs de court, moyen et long termes assignés à la DSI.
D68: Alignement des objectifs avec la stratégie de l’organisation | E68: Les objectifs sont-ils déclinés de manière opérationnelle dans les différentes entités ? | F68: PAS | G68: Plans opérationnels par entité, Contrats d'objectifs métiers | H68: Objectifs non-pertinents ne soutiennent pas la stratégie. | I68: Faible | J68: Objectifs non-pertinents ne soutiennent pas la stratégie. | K68: Aligner les objectifs avec la stratégie de l'organisation.
D69: Déclinaison des objectifs au sein des différentes entités | E69: L’évolution des objectifs est-elle suivie à l’aide d’indicateurs mesurables ? | F69: PAS | G69: Tableaux de bord d'indicateurs, Système de suivi BSC | H69: Manque de coordination cause des actions désalignées. | I69: Faible | J69: Manque de coordination cause des actions désalignées. | K69: Décliner les objectifs au sein des différentes entités.
D70: Suivi de l’évolution des objectifs à travers des indicateurs mesurables | E70: Une approche de type Balanced Scorecard (BSC) ou équivalent est-elle mise en place pour le suivi des objectifs ? | F70: PAS | G70: Documentation méthodologique BSC, Rapports de performance | H70: Manque de suivi quantitatif rend l'évaluation impossible. | I70: Faible | J70: Manque de suivi quantitatif rend l'évaluation impossible. | K70: Suivre l'évolution des objectifs à travers des indicateurs mesurables.
D71: Mise en place d’une approche BSC (Balanced Scorecard) ou équivalent pour le suivi des objectifs | E71: Un comité informatique regroupant les différentes directions est-il en place ? | F71: OUI | G71: PV de création du comité, Composition nominative du comité | H71: Absence d'approche BSC mène à un suivi inefficace. | I71: Faible | J71: Absence d'approche BSC mène à un suivi inefficace. | K71: Mettre en place une approche BSC (Balanced Scorecard) ou équivalent pour le suivi des objectifs.
C72: Vérifier l’existence d’un comité informatique regroupant les différentes directions de l’organisation | D72: Existence d’un comité informatique regroupant les différentes directions | E72: Le comité est-il composé de représentants issus des différentes directions de l’organisation ? | F72: OUI | G72: Liste des représentants par direction, PV de désignation | H72: Comité informatique incomplet limite la coordination. | I72: Elevée | J72: Comité informatique incomplet limite la coordination. | K72: Composer le comité avec des représentants des différentes directions.
D73: Composition du comité avec des représentants des différentes directions | E73: Le comité informatique se réunit-il à une fréquence suffisante ? | F73: OUI | G73: Calendrier des réunions, Historique des participations | H73: Composition inadéquate du comité cause des décisions biaisées. | I73: Elevée | J73: Composition inadéquate du comité cause des décisions biaisées. | K73: Choisir des membres du comité avec une expertise et une représentation équilibrée.
D74: Fréquence des réunions du comité informatique | E74: Les décisions prises au sein du comité informatique sont-elles pertinentes et documentées ? | F74: OUI | G74: Registre des décisions, Analyses d'impact des décisions | H74: Réunions peu fréquentes ralentissent la prise de décision. | I74: Elevée | J74: Réunions peu fréquentes ralentissent la prise de décision. | K74: Augmenter la fréquence des réunions du comité informatique.
D75: Propriétés des décisions prises au sein du comité informatique | E75: Les rôles et responsabilités des membres du comité sont-ils clairement définis ? | F75: OUI | G75: Charte de gouvernance, Matrice RACI des membres | H75: Décisions floues du comité entraînent des interprétations divergentes. | I75: Moyenne | J75: Décisions floues du comité entraînent des interprétations divergentes. | K75: Propriétés des décisions prises au sein du comité informatique.
D76: Clarté des rôles et responsabilités des membres du comité | E76: Les indicateurs de qualité et de performance sont-ils pertinents ? | F76: OUI | G76: Référentiel d'indicateurs, Cartographie indicateurs/objectifs | H76: Rôles et responsabilités mal définis causent des conflits. | I76: Elevée | J76: Rôles et responsabilités mal définis causent des conflits. | K76: Clarifier les rôles et responsabilités des membres du comité.
C77: Évaluer la pertinence des indicateurs de qualité et de performance ainsi que les moyens et outils de mesure | D77: Pertinence des indicateurs de qualité et de performance | E77: Les indicateurs sont-ils exhaustifs et alignés avec les objectifs de la DSI ? | F77: OUI | G77: Matrice de couverture indicateurs, Analyse des écarts | H77: Indicateurs de qualité non pertinents ne reflètent pas la performance. | I77: Elevée | J77: Indicateurs de qualité non pertinents ne reflètent pas la performance. | K77: Choisir des indicateurs de qualité et de performance pertinents.
D78: Exhaustivité et alignement des indicateurs avec les objectifs DSI | E78: Les moyens et outils de mesure sont-ils adaptés aux indicateurs définis ? | F78: OUI | G78: Description des outils de mesure, Procédures de collecte | H78: Indicateurs incomplets ne couvrent pas tous les objectifs. | I78: Elevée | J78: Indicateurs incomplets ne couvrent pas tous les objectifs. | K78: Assurer l'exhaustivité et l'alignement des indicateurs avec les objectifs DSI.
D79: Adéquation des moyens et outils de mesure avec les indicateurs | E79: Les données recueillies sont-elles précises et fiables ? | F79: PAS | G79: Audits de qualité des données, Rapports de fiabilité | H79: Moyens de mesure inadéquats rendent les indicateurs peu fiables. | I79: Moyenne | J79: Moyens de mesure inadéquats rendent les indicateurs peu fiables. | K79: Adapter les moyens et outils de mesure avec les indicateurs.
D80: Précision et fiabilité des données recueillies | E80: Les indicateurs sont-ils suivis et ajustés de manière régulière ? | F80: PAS | G80: Procédures de révision, Historique des ajustements | H80: Données imprécises mènent à des analyses erronées. | I80: Moyenne | J80: Données imprécises mènent à des analyses erronées. | K80: Assurer la précision et la fiabilité des données recueillies.
D81: Suivi et ajustement réguliers des indicateurs | E81: Les indicateurs sont-ils suivis et ajustés régulièrement ? | F81: PAS | G81: Modèle de tableau de bord, Documentation méthodologique | H81: Suivi irrégulier des indicateurs manque des opportunités d'ajustement. | I81: Moyenne | J81: Suivi irrégulier des indicateurs manque des opportunités d'ajustement. | K81: Suivre et ajuster régulièrement les indicateurs.
C82: Vérifier que la DSI tient un tableau de bord (idéalement de type BSC) permettant un suivi consolidé de la performance (opérationnelle et financière) et de la qualité des prestations informatiques | D82: Existence d’un tableau de bord consolidé pour la performance de la DSI | E82: Un tableau de bord consolidé pour évaluer la performance de la DSI existe-t-il ? | F82: PAS | G82: Cartographie BSC, Normes de reporting | H82: Tableau de bord inexistant empêche une vision globale. | I82: Elevée | J82: Tableau de bord inexistant empêche une vision globale. | K82: Mettre en place un tableau de bord consolidé pour la performance de la DSI.
D83: Structure du tableau de bord conforme aux bonnes pratiques de gestion (BSC idéalement) | E83: La structure du tableau de bord est-elle conforme aux bonnes pratiques de gestion, notamment le modèle BSC ? | F83: PAS | G83: Catalogue d'indicateurs opérationnels/financiers | H83: Structure du tableau de bord non conforme limite son utilité. | I83: Moyenne | J83: Structure du tableau de bord non conforme limite son utilité. | K83: Structurer le tableau de bord conformément aux bonnes pratiques de gestion (BSC idéalement).
D84: Suivi opérationnel et financier via des indicateurs clairement définis | E84: Le suivi opérationnel et financier est-il effectué à l’aide d’indicateurs clairement définis ? | F84: PAS | G84: Calendrier de mise à jour, Listes de diffusion | H84: Suivi opérationnel et financier insuffisant nuit à la gestion. | I84: Moyenne | J84: Suivi opérationnel et financier insuffisant nuit à la gestion. | K84: Suivre opérationnellement et financièrement via des indicateurs clairement définis.
D85: Mise à jour régulière du tableau de bord et communication des résultats aux parties prenantes | E85: Le tableau de bord est-il mis à jour régulièrement et ses résultats sont-ils communiqués aux parties prenantes ? | F85: PAS | G85: PV de comités de pilotage, Décisions stratégiques documentées | H85: Mise à jour irrégulière du tableau de bord rend les données obsolètes. | I85: Moyenne | J85: Mise à jour irrégulière du tableau de bord rend les données obsolètes. | K85: Mettre à jour régulièrement le tableau de bord et communiquer les résultats aux parties prenantes.
D86: Utilisation du tableau de bord pour la prise de décision stratégique et opérationnelle | E86: Le tableau de bord est-il utilisé pour prendre des décisions stratégiques et opérationnelles ? | F86: PAS | G86: Modèles de bilan projet, Checklists d'évaluation | H86: Tableau de bord non utilisé limite la prise de décision. | I86: Moyenne | J86: Tableau de bord non utilisé limite la prise de décision. | K86: Utiliser le tableau de bord pour la prise de décision stratégique et opérationnelle.
C87: Vérifier qu’il est systématiquement effectué un bilan après chaque projet et notamment un bilan économique (bilan rapproché des prévisions de l’étude préalable) | D87: Réalisation d’un bilan systématique après chaque projet | E87: Un bilan est-il systématiquement réalisé après chaque projet informatique ? | F87: OUI | G87: Analyses coûts/bénéfices, Rapports d'écarts | H87: Bilan de projet inexistant manque des opportunités d'apprentissage. | I87: Moyenne | J87: Bilan de projet inexistant manque des opportunités d'apprentissage. | K87: Réaliser un bilan systématique après chaque projet.
D88: Analyse économique des projets comparée aux prévisions initiales | E88: Une analyse économique des projets est-elle effectuée et comparée aux prévisions initiales ? | F88: OUI | G88: Registre des améliorations, Plans d'action | H88: Analyse économique absente empêche l'évaluation des projets. | I88: Moyenne | J88: Analyse économique absente empêche l'évaluation des projets. | K88: Analyser économiquement les projets comparés aux prévisions initiales.
D89: Identification des points d'amélioration à partir des bilans réalisés | E89: Les points d'amélioration sont-ils identifiés à partir des bilans réalisés ? | F89: OUI | G89: Suivi des recommandations, Historique des corrections | H89: Points d'amélioration non identifiés perpétuent les inefficacités. | I89: Moyenne | J89: Points d'amélioration non identifiés perpétuent les inefficacités. | K89: Identifier les points d'amélioration à partir des bilans réalisés.
D90: Suivi de l'impact des résultats des bilans sur les projets futurs | E90: L’impact des résultats des bilans sur les projets futurs est-il suivi ? | F90: OUI | G90: PV de restitution, Supports de communication | H90: Impact des bilans non suivi limite l'amélioration continue. | I90: Elevée | J90: Impact des bilans non suivi limite l'amélioration continue. | K90: Suivre l'impact des résultats des bilans sur les projets futurs.
D91: Partage des bilans avec les parties prenantes concernées | E91: Les bilans sont-ils partagés avec les parties prenantes concernées ? | F91: OUI | G91: Organigramme officiel, Dernière version datée | H91: Bilans non partagés entravent la communication. | I91: Elevée | J91: Bilans non partagés entravent la communication. | K91: Partager les bilans avec les parties prenantes concernées.
B92: Organisation et structure de la DSI ; | C92: Vérifier l’existence d’un organigramme à jour de la DSI | D92: Existence d’un organigramme à jour de la DSI | E92: Un organigramme à jour de la DSI est-il disponible ? | F92: OUI | G92: Journal des modifications, Demandes d'évolution | H92: Organigramme inexistant empêche la clarté organisationnelle. | I92: Elevée | J92: Organigramme inexistant empêche la clarté organisationnelle. | K92: Mettre en place un organigramme à jour de la DSI.
D93: Mise à jour régulière de l’organigramme en fonction des évolutions internes | E93: L’organigramme est-il régulièrement mis à jour en fonction des évolutions internes ? | F93: OUI | G93: Guide d'organisation, FAQ interne | H93: Mise à jour irrégulière de l'organigramme le rend obsolète. | I93: Moyenne | J93: Organigramme obsolète ne reflète plus la réalité. | K93: Mettre à jour régulièrement l'organigramme en fonction des évolutions internes.
D94: Clarté de l’organigramme et de ses fonctions pour les employés | E94: L’organigramme et ses fonctions sont-ils clairs pour les employés ? | F94: OUI | G94: Politique de diffusion, Accusés de lecture | H94: Organigramme flou cause des confusions. | I94: Faible | J94: Confusions et manque de clarté organisationnelle. | K94: Clarifier l'organigramme et ses fonctions pour les employés.
D95: Consultation facile de l’organigramme pour toutes les parties prenantes | E95: L’organigramme est-il facilement consultable par toutes les parties prenantes ? | F95: OUI | G95: Rapports d'audit organisationnel, Analyses d'adéquation | H95: Consultation difficile de l'organigramme limite sa diffusion. | I95: Faible | J95: Difficulté de diffusion et manque de compréhension de l'organisation. | K95: Faciliter la consultation de l'organigramme pour toutes les parties prenantes.
D96: Conformité de l’organigramme avec la structure actuelle de la DSI | E96: L’organigramme est-il conforme à la structure actuelle de la DSI ? | F96: OUI | G96: Référentiel des fonctions, Descriptions de poste | H96: Organigramme non conforme ne reflète pas la réalité. | I96: Faible | J96: Organigramme non conforme ne reflète pas la structure actuelle de la DSI. | K96: Assurer la conformité de l'organigramme avec la structure actuelle de la DSI.
C97: Vérifier l’existence d’une définition de fonction et d’un partage clair des rôles et des responsabilités pour chaque poste figurant sur l’organigramme | D97: Existence d’une définition de fonction et d’un partage clair des rôles et responsabilités | E97: Une définition de fonction existe-t-elle, avec un partage clair des rôles et responsabilités ? | F97: OUI | G97: Matrices de compétences, Fiches de mission | H97: Définition de fonction inexistante cause des chevauchements de rôles. | I97: Faible | J97: Chevauchements de rôles et manque de clarté dans les responsabilités. | K97: Définir les fonctions et établir une définition claire des rôles et responsabilités.
D98: Clarté des descriptions de fonction et des responsabilités associées | E98: Les descriptions de fonction et les responsabilités associées sont-elles claires ? | F98: OUI | G98: Fiche de poste détaillée, Manuel des procédures internes | H98: Descriptions de fonction floues entraînent des malentendus. | I98: Faible | J98: Malentendus et manque de clarté dans les attentes. | K98: Clarifier les descriptions de fonction et les responsabilités associées.
D99: Attribution de rôles en fonction des compétences et des besoins organisationnels | E99: Les rôles sont-ils attribués en fonction des compétences et des besoins organisationnels ? | F99: OUI | G99: Grille de compétences, Procès-verbal de réunion RH / DSI sur les affectations | H99: Rôles mal attribués causent des inefficacités. | I99: Elevée | J99: Inefficacités et manque de coordination. | K99: Attribuer les rôles en fonction des compétences et des besoins organisationnels.
D100: Mise à jour régulière des descriptions de fonction | E100: Les descriptions de fonction sont-elles mises à jour régulièrement ? | F100: OUI | G100: Historique des versions des fiches de poste, Rapport annuel de révision des fonctions | H100: Mise à jour irrégulière des descriptions les rend obsolètes. | I100: Elevée | J100: Descriptions de fonction obsolètes ne reflètent plus les réalités. | K100: Mettre à jour régulièrement les descriptions de fonction.
...

Sheet 4.3
A1: Domaines | B1: Points de Contrôle | C1: Objectifs de contrôle | D1: Critères d’évaluation | E1: Question d’Évaluation | F1: Réponses | G1: Documents Requis | H1: Risques | I1: Criticité | J1: Conséquences | K1: Recommandations
A2: PROJET INFORMATQUE | B2: Objectifs et enjeux du projet | C2: S’assurer qu’une étude de la valeur et des études d'opportunité et d'impacts ont été réalisées | D2: Existence d’une étude de faisabilité documentée et validée | E2: Une étude de faisabilité a-t-elle été documentée et validée ? | F2: OUI | G2: Note de cadrage, Étude de faisabilité | H2: Mauvais cadrage du projet | I2: Moyenne | J2: Dérives budgétaires et retard important | K2: Élaborer une étude préalable approfondie avec validation directionnelle
D3: Analyse des opportunités et menaces associées réalisée et archivée | E3: L’analyse des opportunités et menaces associées a-t-elle été réalisée et archivée ? | F3: OUI | G3: Analyse SWOT, Rapport d’analyse stratégique | H3: Opportunités manquées | I3: Elevée | J3: Avantages potentiels non réalisés | K3: Mettre en place un processus formel d'identification des opportunités
D4: Prise en compte des impacts organisationnels et financiers évalués | E4: Les impacts organisationnels et financiers ont-ils été évalués et pris en compte ? | F4: OUI | G4: Étude d’impact, Étude financière | H4: Sous-estimation des coûts | I4: Elevée | J4: Dépenses imprévues impactant la rentabilité | K4: Réaliser une estimation détaillée avec buffer de sécurité (+20%)
D5: Consultation des parties prenantes attestée et rapportée | E5: La consultation des parties prenantes a-t-elle été attestée et rapportée ? | F5: NON | G5: Compte rendu de réunion, Feuille de présence | H5: Mauvaise adhésion des parties | I5: Faible | J5: Résistance au changement et échec d'adoption | K5: Impliquer les utilisateurs dès la phase de conception
C6: S’assurer qu’un bilan critique des processus existants a été effectué | D6: Décision formelle sur la pertinence du projet disponible | E6: Une décision formelle sur la pertinence du projet est-elle disponible ? | F6: OUI | G6: Décision de GO/NOGO, Compte rendu de comité | H6: Lancement d’un projet non pertinent | I6: Elevée | J6: Gaspillage de ressources sur des objectifs non stratégiques | K6: Aligner systématiquement les projets sur la roadmap stratégique
D7: Rapport d’analyse des processus actuels disponible et validé | E7: Un rapport d’analyse des processus actuels est-il disponible et validé ? | F7: PAS | G7: Rapport d’analyse des processus, Document de validation | H7: Solutions inadaptées | I7: Moyenne | J7: Solution ne répondant pas aux besoins | K7: Valider les spécifications via des prototypes et tests utilisateurs
D8: Identification des dysfonctionnements et points d’amélioration répertoriés | E8: Les dysfonctionnements et points d’amélioration ont-ils été identifiés et répertoriés ? | F8: OUI | G8: Liste des dysfonctionnements, Plan d’amélioration | H8: Pérennisation des erreurs | I8: Elevée | J8: Répétition des mêmes erreurs projet après projet | K8: Capitaliser les retours d'expérience dans un référentiel partagé
D9: Comparaison des performances actuelles avec des indicateurs de référence | E9: Les performances actuelles ont-elles été comparées à des indicateurs de référence ? | F9: PAS | G9: Rapport de comparaison, Tableau d’indicateurs | H9: Mauvaise mesure de performance | I9: Moyenne | J9: Impossibilité d'évaluer la réussite | K9: Définir des KPIs SMART avant le lancement
D10: Validation des conclusions du bilan par les instances de gouvernance | E10: Les conclusions du bilan ont-elles été validées par les instances de gouvernance ? | F10: OUI | G10: Procès-verbal de validation, Compte rendu de gouvernance | H10: Absence de soutien décisionnel | I10: Moyenne | J10: Prise de décision sans données fiables | K10: Implémenter des tableaux de bord décisionnels temps réel
C11: S’assurer que le choix de recourir à un nouveau système est obtenu après optimisation des processus concernés et vérification que cette optimisation ne suffit pas à apporter par elle-même les gains de performance attendus | D11: Documentation des processus cartographiée et mise à jour | E11: La documentation des processus a-t-elle été cartographiée et mise à jour ? | F11: OUI | G11: Cartographie des processus, Référentiel des procédures | H11: Incohérences fonctionnelles | I11: Elevée | J11: Incompatibilités techniques et dysfonctionnements | K11: Établir une architecture de référence contraignante
D12: Compte-rendu de l’optimisation des processus concernés établi | E12: Un compte-rendu de l’optimisation des processus concernés a-t-il été établi ? | F12: OUI | G12: Compte-rendu d’optimisation, Rapport d’audit | H12: Optimisation inefficace | I12: Moyenne | J12: Gains insuffisants par rapport aux coûts | K12: Prioriser les initiatives par analyse coûts/bénéfices
D13: Indicateurs de performance avant et après optimisation analysés | E13: Les indicateurs de performance avant et après optimisation ont-ils été analysés ? | F13: PAS | G13: Rapport d’indicateurs, Tableau comparatif | H13: Impact non mesuré | I13: Moyenne | J13: Impacts réels inconnus | K13: Prévoir un plan de mesure d'impact post-déploiement
D14: Justification technique et économique de l’abandon d’une simple amélioration disponible | E14: La justification technique et économique de l’abandon d’une simple amélioration est-elle disponible ? | F14: OUI | G14: Rapport d’évaluation, Analyse économique | H14: Investissements injustifiés | I14: Moyenne | J14: Dépenses sans retour sur investissement | K14: Exiger une business case validée par la direction financière
D15: Évaluation des gains obtenus par optimisation seule insuffisants formalisée | E15: Les gains obtenus par l’optimisation seule ont-ils été évalués et jugés insuffisants ? | F15: OUI | G15: Document comparatif, Étude de faisabilité | H15: Solution non optimale retenue | I15: Moyenne | J15: Choix sous-optimal pénalisant l'organisation | K15: Appliquer une méthode multicritère de sélection rigoureuse
C16: S’assure que les objectifs et périmètres du projet sont définis, partagés et stabilisés | D16: Analyse comparative entre optimisation et solution nouvelle réalisée | E16: Une analyse comparative entre optimisation et solution nouvelle a-t-elle été réalisée ? | F16: OUI | G16: Document de cadrage, Note de lancement | H16: Objectifs flous | I16: Moyenne | J16: Incompréhension des attentes | K16: Formaliser un document d'orientation projet signé par toutes les parties
D17: Document de cadrage du projet rédigé et diffusé | E17: Le document de cadrage du projet a-t-il été rédigé et diffusé ? | F17: OUI | G17: Objectifs validés, Feuille de route | H17: Dérive des livrables | I17: Elevée | J17: Livraisons ne correspondant pas aux attentes | K17: Mettre en place des jalons de validation intermédiaires
D18: Objectifs mesurables, atteignables et datés validés par la direction | E18: Les objectifs ont-ils été mesurables, atteignables et validés par la direction ? | F18: NON | G18: Document de périmètre, Cahier des charges | H18: Travaux hors périmètre | I18: Faible | J18: Augmentation non maîtrisée des coûts | K18: Instaurer un strict contrôle du périmètre et processus de changement
D19: Définition claire des périmètres fonctionnels et techniques actée | E19: La définition des périmètres fonctionnels et techniques a-t-elle été clairement actée ? | F19: OUI | G19: Actes de validation, Relevés de décisions | H19: Non-alignement stratégique | I19: Faible | J19: Projet devenu obsolète ou inutile | K19: Réaliser des points d'alignement stratégique trimestriels
D20: Actes de validation et de partage des objectifs accessibles | E20: Les actes de validation et de partage des objectifs sont-ils accessibles ? | F20: OUI | G20: Plan de gestion des risques, Tableau de contraintes | H20: Ignorance des risques majeurs | I20: Moyenne | J20: Surprise par des problèmes majeurs | K20: Effectuer une analyse de risques approfondie en amont
C21: S’assurer que les principales orientations du système cible ont été explicitées | D21: Prise en compte des contraintes et risques identifiés | E21: Les contraintes et risques identifiés ont-ils été pris en compte ? | F21: OUI | G21: Spécifications techniques, Schémas fonctionnels | H21: Solution mal adaptée | I21: Moyenne | J21: Solution technique inappropriée | K21: Valider les choix techniques par un comité d'experts indépendants
D22: Description fonctionnelle et technique du système cible disponible | E22: La description fonctionnelle et technique du système cible est-elle disponible ? | F22: OUI | G22: Comparatif technologique, Compte rendu d’arbitrage | H22: Choix technique contesté | I22: Elevée | J22: Conflits et rejet de la solution | K22: Organiser des preuves de concept avant sélection finale
D23: Options technologiques étudiées et arbitrages justifiés | E23: Les options technologiques ont-elles été étudiées et les arbitrages justifiés ? | F23: OUI | G23: Document d’architecture, Note d’intégration | H23: Incompatibilité avec l’existant | I23: Moyenne | J23: Problèmes d'interfaçage et de compatibilité | K23: Élaborer une cartographie détaillée de l'existant
D24: Synthèse des choix d’architecture et d’intégration rédigée | E24: Une synthèse des choix d’architecture et d’intégration a-t-elle été rédigée ? | F24: PAS | G24: Compte rendu de validation, PV de comité | H24: Refus de mise en œuvre | I24: Moyenne | J24: Refus des équipes d'utiliser la solution | K24: Mener une campagne d'adhésion en amont avec les opérationnels
D25: Validation des orientations par les instances décisionnelles | E25: Les orientations ont-elles été validées par les instances décisionnelles ? | F25: OUI | G25: Étude d’impact, Analyse de compatibilité | H25: Défaillance en production | I25: Faible | J25: Incidents répétés en production | K25: Instaurer des environnements de pré-production et tests rigoureux
C26: S’assurer que les principaux acteurs sont identifiés | D26: Analyse d’impacts et de compatibilité réalisée | E26: Une analyse d’impacts et de compatibilité a-t-elle été réalisée ? | F26: OUI | G26: Liste des acteurs, Organigramme projet | H26: Responsabilités floues | I26: Moyenne | J26: Confusion dans l'exécution des tâches | K26: Élaborer une matrice RACI détaillée pour toutes les activités
D27: Liste nominative et rôle des acteurs recensés | E27: La liste nominative et le rôle des acteurs ont-ils été recensés ? | F27: OUI | G27: Registre des parties, Documents de validation | H27: Parties prenantes oubliées | I27: Moyenne | J27: Besoins spécifiques ignorés | K27: Identifier et consulter toutes les parties prenantes en amont
D28: Acteurs internes et externes intégrés et validés | E28: Les acteurs internes et externes ont-ils été intégrés et validés ? | F28: OUI | G28: Tableau des responsabilités, RACI | H28: Conflits de rôles | I28: Elevée | J28: Conflits d'intérêts et chevauchements | K28: Clarifier les rôles et responsabilités dans une charte projet
D29: Tableau de répartition des responsabilités établi | E29: Un tableau de répartition des responsabilités a-t-il été établi ? | F29: PAS | G29: Feuilles de présence, Comptes rendus | H29: Engagement non vérifié | I29: Moyenne | J29: Engagements non tenus | K29: Mettre en place un suivi formel des engagements avec compte-rendu
D30: Actes de participation et comptes rendus des réunions disponibles | E30: Les actes de participation et les comptes rendus des réunions sont-ils disponibles ? | F30: OUI | G30: Cartographie des acteurs, Registre des parties | H30: Manque d’alignement | I30: Moyenne | J30: Objectifs divergents entre équipes | K30: Organiser des ateliers d'alignement inter-services
B31: Étude d'opportunité et expression des besoins | C31: S’assurer que l'expression détaillée des besoins est formalisée dans un cahier des charges fait par la MOA | D31: Cartographie des parties prenantes mise à jour | E31: La cartographie des parties prenantes a-t-elle été mise à jour ? | F31: OUI | G31: Fiche de recueil des besoins, Questionnaire utilisateurs | H31: Besoins mal identifiés | I31: Moyenne | J31: Solution ne répondant pas aux attentes | K31: Formaliser un cahier des charges exhaustif et validé
D32: Recueil formalisé des besoins utilisateurs validé | E32: Le recueil des besoins utilisateurs a-t-il été formalisé et validé ? | F32: OUI | G32: Fiches de recueil des besoins, Procès-verbal de validation des besoins | H32: Inadéquation entre les besoins réels et la solution livrée | I32: Elevée | J32: Écart entre ce qui est livré et ce qui est attendu | K32: Impliquer régulièrement le maître d'ouvrage dans les validations
D33: Cahier des charges structuré et signé par la MOA | E33: Le cahier des charges a-t-il été structuré et signé par la MOA ? | F33: OUI | G33: Cahier des charges complet, Signature de la MOA | H33: Non-alignement du projet avec les attentes du maître d’ouvrage | I33: Moyenne | J33: Perte de vue des objectifs initiaux | K33: Référencer systématiquement aux documents initiaux dans les revues
D34: Traçabilité des besoins vers les exigences fonctionnelles assurée | E34: La traçabilité des besoins vers les exigences fonctionnelles est-elle assurée ? | F34: OUI | G34: Cahier des charges, Matrice de traçabilité des exigences | H34: Perte de lien entre besoins initiaux et développement | I34: Moyenne | J34: Ressources insuffisantes ou délais irréalistes | K34: Appliquer une méthode de planification rigoureuse (type PERT)
D35: Priorisation des besoins justifiée et documentée | E35: La priorisation des besoins a-t-elle été justifiée et documentée ? | F35: PAS | G35: Document de priorisation, Justificatif de classement | H35: Mauvaise allocation des ressources ou délais mal évalués | I35: Moyenne | J35: Conflits sur la finalité du projet | K35: Documenter et faire valider les objectifs par toutes les parties
C36: S’assurer que le cahier des charges préconise une solution fonctionnellement et techniquement pertinente au regard des besoins exprimés | D36: Validation conjointe MOA et parties prenantes attestée | E36: La validation conjointe de la MOA et des parties prenantes a-t-elle été attestée ? | F36: PAS | G36: PV de réunion de validation, Signatures MOA et parties prenantes | H36: Désaccords ultérieurs sur les objectifs du projet | I36: Moyenne | J36: Incompréhension des besoins réels | K36: Organiser des ateliers de conception collaboratifs
D37: Cahier des charges comportant les exigences fonctionnelles et techniques détaillées | E37: Le cahier des charges comporte-t-il les exigences fonctionnelles et techniques détaillées ? | F37: PAS | G37: Cahier des charges détaillé, Annexe technique fonctionnelle | H37: Spécifications insuffisantes ou mal interprétées | I37: Moyenne | J37: Solution technique inadaptée aux usages | K37: Privilégier les approches user-centric design
D38: Adéquation entre besoins exprimés et solution proposée vérifiée | E38: L’adéquation entre les besoins exprimés et la solution proposée a-t-elle été vérifiée ? | F38: PAS | G38: Matrice de validation, Rapport d’évaluation de conformité | H38: Conception d'une solution inadaptée | I38: Moyenne | J38: ROI négatif ou insuffisant | K38: Réaliser une analyse financière approfondie en amont
D39: Analyse comparative des solutions candidates effectuée | E39: Une analyse comparative des solutions candidates a-t-elle été effectuée ? | F39: PAS | G39: Tableau comparatif des solutions, Rapport d’analyse multicritère | H39: Choix d’une solution inefficace ou coûteuse | I39: Moyenne | J39: Problèmes juridiques ou techniques imprévus | K39: Effectuer une revue légale et technique complète
D40: Solution retenue validée au regard des performances attendues | E40: La solution retenue a-t-elle été validée au regard des performances attendues ? | F40: PAS | G40: PV de validation de la solution, Rapport de tests de performance | H40: Mauvais retour sur investissement | I40: Moyenne | J40: Besoins d'utilisateurs clés ignorés | K40: Cartographier l'ensemble des personas utilisateurs
C41: S’assurer que les exigences utilisateurs, les populations ciblées, les options et principes de gestion retenus sont précisés et priorisés | D41: Prise en compte des contraintes réglementaires et normatives attestée | E41: Les contraintes réglementaires et normatives ont-elles été prises en compte et attestées ? | F41: PAS | G41: Document de conformité réglementaire, Fiche de contrôle normatif | H41: Sanctions légales ou incompatibilités techniques | I41: Moyenne | J41: Retards dans les arbitrages | K41: Désigner un comité de pilotage avec pouvoir de décision
D42: Liste des exigences utilisateurs et des populations cibles définie | E42: La liste des exigences utilisateurs et des populations cibles a-t-elle été définie ? | F42: PAS | G42: Liste des exigences utilisateurs, Fiches des profils utilisateurs | H42: Oubli de certaines catégories d’utilisateurs | I42: Elevée | J42: Mauvaises options de gestion choisies | K42: Établir un cadre décisionnel clair avec critères de choix
D43: Analyse des priorités et arbitrages formalisée | E43: L’analyse des priorités et arbitrages a-t-elle été formalisée ? | F43: PAS | G43: Matrice de priorisation, Rapport d’arbitrage | H43: Retards ou conflits dans les décisions fonctionnelles | I43: Moyenne | J43: Priorités contradictoires | K43: Hiérarchiser les objectifs selon la stratégie globale
D44: Critères de sélection des options de gestion explicités | E44: Les critères de sélection des options de gestion ont-ils été explicités ? | F44: PAS | G44: Grille de critères, PV d’arbitrage | H44: Mauvaise sélection des options de gestion | I44: Moyenne | J44: Projet devenu incohérent avec la stratégie | K44: Mettre en place des revues d'alignement stratégique
D45: Document de synthèse des exigences et choix de gestion rédigé | E45: Un document de synthèse des exigences et des choix de gestion a-t-il été rédigé ? | F45: OUI | G45: Document de synthèse, Feuille de route fonctionnelle | H45: Objectifs flous ou contradiction dans les choix | I45: Moyenne | J45: Difficultés d'intégration technique | K45: Réaliser une étude d'intégration approfondie
C46: S’assurer que le projet est cohérent avec le plan directeur informatique | D46: Alignement du projet avec les orientations stratégiques du plan directeur validé | E46: L’alignement du projet avec les orientations stratégiques du plan directeur a-t-il été validé ? | F46: PAS | G46: Note de cadrage stratégique, PV de réunion de validation | H46: Décrochage avec la vision globale de l’organisation | I46: Moyenne | J46: Décisions contraires à la feuille de route SI | K46: Nommer un architecte SI comme gardien de la cohérence
D47: Analyse de cohérence effectuée entre le projet et le plan directeur informatique | E47: Une analyse de cohérence a-t-elle été effectuée entre le projet et le plan directeur informatique ? | F47: PAS | G47: Document de cohérence, Rapport d’alignement stratégique | H47: Problèmes d'intégration dans l’écosystème SI | I47: Moyenne | J47: Manque de support technique en cas de problème | K47: Formaliser un accord de service avec la DSI
D48: Références explicites au plan directeur dans la documentation du projet | E48: Des références explicites au plan directeur figurent-elles dans la documentation du projet ? | F48: PAS | G48: Documentation projet, Références plan directeur mentionnées | H48: Décisions prises en contradiction avec le plan directeur | I48: Moyenne | J48: Blocages dans les prises de décision | K48: Définir un mode de gouvernance clair avec processus d'escalade
D49: Avis formel de la direction des systèmes d'information disponible | E49: Un avis formel de la direction des systèmes d'information est-il disponible ? | F49: PAS | G49: Avis écrit de la DSI, Courrier officiel de validation | H49: Absence de soutien de la DSI en cas de problème | I49: Moyenne
D50: Validation par les instances en charge du plan directeur obtenue | E50: La validation par les instances en charge du plan directeur a-t-elle été obtenue ? | F50: PAS | G50: PV de comité de validation, Rapport de synthèse | H50: Blocage dans la gouvernance du projet | I50: Moyenne
C51: S’assurer que le projet est cohérent avec le SI actuel ou futur | D51: Comparaison du projet avec l’architecture du SI en place ou prévue réalisée | E51: Une comparaison du projet avec l’architecture du SI en place ou prévue a-t-elle été réalisée ? | F51: PAS | G51: Schéma d’architecture cible, Comparatif de l’existant | H51: Mauvaise intégration avec l’architecture SI actuelle | I51: Moyenne
D52: Analyse d’impacts sur le SI existant formalisée | E52: L’analyse d’impacts sur le SI existant a-t-elle été formalisée ? | F52: PAS | G52: Fiche d’impact SI, Rapport d’analyse technique | H52: Risques de perturbation sur les systèmes existants | I52: Elevée
D53: Études de compatibilité technique avec les composants du SI disponibles | E53: Des études de compatibilité technique avec les composants du SI sont-elles disponibles ? | F53: PAS | G53: Études techniques, Tests de compatibilité | H53: Incompatibilité avec les outils en place | I53: Moyenne
D54: Recommandations d’urbanisation respectées dans la solution choisie | E54: Les recommandations d’urbanisation ont-elles été respectées dans la solution choisie ? | F54: OUI | G54: Rapport d’urbanisation, Grille de conformité | H54: Fragmentation ou redondance du SI | I54: Moyenne
D55: Avis des architectes SI ou du responsable urbanisation intégré au dossier | E55: L’avis des architectes SI ou du responsable urbanisation a-t-il été intégré au dossier ? | F55: OUI | G55: PV des comités, Fiches de participation | H55: Mauvais pilotage du projet | I55: Moyenne
C56: S’assurer que la direction est bien impliquée dans le projet | D56: Présence de la direction dans les comités de pilotage attestée | E56: La présence de la direction dans les comités de pilotage a-t-elle été attestée ? | F56: PAS | G56: Compte rendu d’engagement, Plan de suivi stratégique | H56: Abandon partiel ou désengagement de la direction | I56: Moyenne
D57: Engagement formel de la direction dans le suivi du projet documenté | E57: L’engagement formel de la direction dans le suivi du projet a-t-il été documenté ? | F57: PAS | G57: PV des réunions stratégiques, Registre des décisions | H57: Décisions incohérentes ou non suivies | I57: Moyenne
D58: Décisions stratégiques prises par la direction retracées | E58: Les décisions stratégiques prises par la direction ont-elles été retracées ? | F58: OUI | G58: Fiche d’affectation, Lettre d’engagement de ressources | H58: Manque de moyens humains ou financiers | I58: Moyenne
D59: Ressources clés allouées par la direction au projet identifiées | E59: Les ressources clés allouées par la direction au projet ont-elles été identifiées ? | F59: PAS | G59: Bulletin d’information, Courriel officiel de la direction | H59: Manque de mobilisation des équipes | I59: Moyenne
D60: Communication de la direction sur le projet observée et tracée | E60: La communication de la direction sur le projet a-t-elle été observée et tracée ? | F60: OUI | G60: Planning consolidé, Gantt partagé | H60: Retards dus à un manque de coordination | I60: Moyenne
B61: Planification | C61: S’assurer qu’il existe un planning directeur commun à tout le projet | D61: Document unique de planification partagé entre les équipes du projet disponible | E61: Un document unique de planification partagé entre les équipes du projet est-il disponible ? | F61: PAS | G61: Plan de projet global, Documents de répartition des responsabilités | H61: Manque de coordination, entraînant des erreurs de synchronisation | I61: Moyenne
D62: Synchronisation des jalons et des tâches entre toutes les parties prenantes assurée | E62: La synchronisation des jalons et des tâches entre toutes les parties prenantes est-elle assurée ? | F62: PAS | G62: Planning directeur du projet, Tableaux de suivi des jalons | H62: Dépendances non respectées, impactant l'avancement du projet | I62: Moyenne
D63: Tableau de bord commun utilisé pour suivre l’avancement du projet | E63: Un tableau de bord commun est-il utilisé pour suivre l’avancement du projet ? | F63: PAS | G63: Tableau de bord de gestion de projet, Rapport d'avancement régulier | H63: Problèmes de communication des progrès, retard dans la mise à jour | I63: Elevée
D64: Réunions de coordination basées sur le planning directeur organisées | E64: Des réunions de coordination basées sur le planning directeur ont-elles été organisées ? | F64: OUI | G64: Agenda des réunions de coordination, Compte rendu des réunions de coordination | H64: Absence de réajustement du projet en fonction des réunions | I64: Elevée
D65: Mise à jour régulière du planning directeur validée par tous les acteurs | E65: La mise à jour régulière du planning directeur a-t-elle été validée par tous les acteurs ? | F65: OUI | G65: Planning mis à jour avec validation, Rapport de révision de planning | H65: Non-respect des délais ou mauvaise anticipation des changements | I65: Elevée
C66: S’assurer qu’il existe un plan de projet initial | D66: Plan de projet formel rédigé, validé et archivé | E66: Le plan de projet a-t-il été formellement rédigé, validé et archivé ? | F66: OUI | G66: Document de validation du plan de projet, Plan de gestion des risques | H66: Absence d'engagement des parties prenantes sur la version validée | I66: Moyenne
D67: Définition claire des phases, activités, livrables et responsabilités dans le plan | E67: Les phases, activités, livrables et responsabilités sont-elles clairement définies dans le plan ? | F67: OUI | G67: Diagramme de Gantt ou chronogramme, Détail des responsabilités par équipe | H67: Délai non respecté, causant des retards dans la livraison des livrables | I67: Moyenne
D68: Approche méthodologique précisée dans le document initial | E68: L’approche méthodologique a-t-elle été précisée dans le document initial ? | F68: OUI | G68: Document d'approche méthodologique, Manuel de procédures et normes du projet | H68: Non-alignement des équipes sur les processus de travail | I68: Moyenne
D69: Lien entre plan de projet et autres documents de pilotage établi | E69: Un lien entre le plan de projet et les autres documents de pilotage a-t-il été établi ? | F69: OUI | G69: Plan de gestion des ressources, Document de gestion des risques | H69: Perte de vue des interrelations, avec des décisions non cohérentes | I69: Elevée
D70: Communication officielle de ce plan à tous les acteurs confirmée | E70: La communication officielle de ce plan à tous les acteurs a-t-elle été confirmée ? | F70: OUI | G70: Procès-verbal de la réunion de lancement du projet, Document de diffusion du plan | H70: Malentendus ou absence de communication, perturbant l'exécution | I70: Elevée
C71: S’assurer que ce plan de projet a été révisé | D71: Justifications des révisions du plan de projet disponibles | E71: Les justifications des révisions du plan de projet sont-elles disponibles ? | F71: OUI | G71: Rapport de justification des modifications, Document d'impact des révisions sur le projet | H71: Résistance au changement, entraînant des modifications non validées | I71: Moyenne
D72: Nouvelle version du plan formellement validée par les instances décisionnelles | E72: Une nouvelle version du plan a-t-elle été formellement validée par les instances décisionnelles ? | F72: OUI | G72: Document de validation par la direction, Acte de validation de la révision | H72: Manque d'alignement stratégique avec la direction | I72: Moyenne
D73: Traçabilité des modifications apportées entre versions assurée | E73: La traçabilité des modifications apportées entre les versions est-elle assurée ? | F73: OUI | G73: Historique des versions du plan, Registre des modifications et approbations | H73: Modifications non documentées, créant de l'ambiguïté dans l'exécution | I73: Moyenne
D74: Révisions intégrant les retours d’expérience ou aléas du projet intégrées | E74: Les révisions intègrent-elles les retours d’expérience ou les aléas du projet ? | F74: OUI | G74: Rapport de retour d'expérience, Plan d'action suite aux retours | H74: Échec à intégrer les leçons apprises, répétition d'erreurs passées | I74: Moyenne
D75: Diffusion du plan révisé à toutes les parties prenantes attestée | E75: La diffusion du plan révisé à toutes les parties prenantes a-t-elle été attestée ? | F75: OUI | G75: Document de confirmation de diffusion, Liste de distribution des plans révisés | H75: Retards dans l'adoption des nouvelles versions par les parties | I75: Moyenne
C76: S’assurer qu’il existe des plans détaillés | D76: Livrables techniques détaillés disponibles pour chaque lot du projet | E76: Les livrables techniques détaillés sont-ils disponibles pour chaque lot du projet ? | F76: OUI | G76: Liste des livrables techniques par lot, Cahier des charges techniques | H76: Livraison incomplète ou incorrecte des livrables | I76: Moyenne
D77: Détail des tâches, ressources, durées et responsabilités précisé dans les plans | E77: Le détail des tâches, ressources, durées et responsabilités est-il précisé dans les plans ? | F77: OUI | G77: Plan de répartition des ressources, Planning des tâches détaillées | H77: Sous-estimation des ressources nécessaires, retardant le projet | I77: Elevée
D78: Validation formelle des plans détaillés par les équipes concernées obtenue | E78: La validation formelle des plans détaillés par les équipes concernées a-t-elle été obtenue ? | F78: OUI | G78: Document de validation des équipes, Plan de validation des tâches | H78: Non-adhésion des équipes aux plans, provoquant des écarts d'exécution | I78: Moyenne
D79: Utilisation des plans détaillés comme référence pour le suivi opérationnel constatée | E79: Les plans détaillés sont-ils utilisés comme référence pour le suivi opérationnel ? | F79: OUI | G79: Rapport de suivi de l'avancement des tâches, Plan de suivi opérationnel | H79: Suivi inefficace, impactant la gestion du projet | I79: Moyenne
D80: Mise à jour continue des plans en fonction de l’avancement vérifiée | E80: La mise à jour continue des plans en fonction de l’avancement a-t-elle été vérifiée ? | F80: OUI | G80: Rapport de mise à jour régulière des plans, Plan de révision périodique | H80: Incohérence dans l'évolution du projet à cause d'une mise à jour mal gérée | I80: Moyenne
C81: S’assurer que ces plans ont été révisés | D81: Historique des révisions des plans disponible et tracé | E81: Un historique des révisions des plans est-il disponible et tracé ? | F81: OUI | G81: Registre de révisions, Rapport des versions précédentes | H81: Perte de contrôle sur les révisions apportées | I81: Moyenne
D82: Validation formelle des versions révisées par les instances de pilotage constatée | E82: La validation formelle des versions révisées par les instances de pilotage a-t-elle été constatée ? | F82: OUI | G82: Acte de validation des versions révisées, Compte rendu des réunions de pilotage | H82: Mauvaise adoption des révisions, conflit avec la direction | I82: Moyenne
D83: Mise à jour des plans en fonction des risques, incidents ou évolutions attestée | E83: La mise à jour des plans en fonction des risques, incidents ou évolutions a-t-elle été attestée ? | F83: OUI | G83: Plan de gestion des risques mis à jour, Document d'évaluation de l'impact des incidents | H83: Problèmes imprévus mal gérés ou ignorés, impactant l'avancement | I83: Elevée
D84: Diffusion des plans révisés à tous les acteurs concernés documentée | E84: La diffusion des plans révisés à tous les acteurs concernés a-t-elle été documentée ? | F84: OUI | G84: Rapport de diffusion des plans révisés, Liste des parties prenantes informées | H84: Absence de diffusion, créant des divergences dans l'exécution | I84: Moyenne
D85: Vérification de la cohérence entre les différentes versions des plans assurée | E85: La cohérence entre les différentes versions des plans a-t-elle été vérifiée ? | F85: OUI | G85: Rapport de vérification de cohérence des versions, Document d'analyse des écarts | H85: Incohérence entre les versions, menant à une mauvaise gestion du projet | I85: Moyenne
B86: Instances de pilotage | C86: S’assurer que la structure de pilotage est formalisée et connue de tous les acteurs | D86: Organigramme de la structure de pilotage rédigé et diffusé | E86: Un organigramme de la structure de pilotage a-t-il été rédigé et diffusé ? | F86: OUI | G86: Organigramme du projet, Document de définition des rôles et responsabilités | H86: Absence de clarté sur la hiérarchie, engendrant une mauvaise gestion des responsabilités | I86: Moyenne
D87: Rôles et responsabilités de chaque acteur clairement définis et validés | E87: Les rôles et responsabilités de chaque acteur ont-ils été clairement définis et validés ? | F87: PAS | G87: Plan de répartition des responsabilités, Acte de validation des rôles et responsabilités | H87: Non-respect des responsabilités, retardant la prise de décision | I87: Moyenne
D88: Présentation officielle de la structure de pilotage à tous les intervenants réalisée | E88: La présentation officielle de la structure de pilotage à tous les intervenants a-t-elle été réalisée ? | F88: OUI | G88: Document de présentation de la structure de pilotage, Rapport de communication du comité | H88: Manque de clarté dans la présentation, entraînant une mauvaise compréhension des rôles | I88: Moyenne
D89: Traçabilité des décisions et des acteurs responsables documentée | E89: La traçabilité des décisions et des acteurs responsables a-t-elle été documentée ? | F89: PAS | G89: Registre des décisions et des responsables, Rapport de suivi des décisions | H89: Mauvaise traçabilité des décisions, créant des conflits ou ambiguïtés | I89: Moyenne
D90: Mise à jour de la structure en cas de changement organisationnel constatée | E90: La structure a-t-elle été mise à jour en cas de changement organisationnel constaté ? | F90: OUI | G90: Document de mise à jour de la structure organisationnelle, Rapport de suivi des changements | H90: Absence de mise à jour en cas de changements organisationnels, créant de la confusion | I90: Moyenne
C91: S’assurer que les différentes instances de pilotage connaissent leurs niveaux de délégation | D91: Documents de délégation de pouvoirs et responsabilités disponibles | E91: Les documents de délégation de pouvoirs et responsabilités sont-ils disponibles ? | F91: PAS | G91: Documents de délégation de pouvoirs, Actes de délégation officiels | H91: Absence de documentation sur les délégations, entraînant une mauvaise gestion des responsabilités | I91: Moyenne
D92: Communication des niveaux de délégation à chaque instance attestée | E92: Les niveaux de délégation ont-ils été communiqués à chaque instance ? | F92: PAS | G92: Rapport de communication des niveaux de délégation, Document de confirmation de réception des informations | H92: Mauvaise communication des délégations, rendant l'exécution difficile | I92: Moyenne
D93: Formation ou briefing sur les délégations réalisé auprès des membres concernés | E93: Une formation ou un briefing sur les délégations a-t-il été réalisé auprès des membres concernés ? | F93: PAS | G93: Programme de formation sur les délégations, Rapport de formation | H93: Non-adoption ou incompréhension des délégations, affectant l'efficacité des équipes | I93: Moyenne
D94: Tableau de synthèse des délégations et pouvoirs validé | E94: Un tableau de synthèse des délégations et pouvoirs a-t-il été validé ? | F94: PAS | G94: Tableau de synthèse des délégations et pouvoirs, Document de validation des délégations | H94: Non-alignement des délégations avec les besoins réels, perturbant l'avancement du projet | I94: Moyenne
D95: Adéquation entre les niveaux de délégation et les responsabilités opérationnelles contrôlée | E95: L’adéquation entre les niveaux de délégation et les responsabilités opérationnelles a-t-elle été contrôlée ? | F95: PAS | G95: Rapport de vérification de l'adéquation des délégations, Document de contrôle interne | H95: Incohérence entre les délégations et les responsabilités réelles, créant des lacunes dans le projet | I95: Elevée
C96: S’assurer que les objectifs des délégations sont atteints | D96: Suivi des indicateurs de performance liés aux délégations disponible | E96: Le suivi des indicateurs de performance liés aux délégations est-il disponible ? | F96: PAS | G96: Tableau de bord de suivi des indicateurs de performance, Rapport d'analyse des performances | H96: Mauvaise gestion des performances déléguées, impactant la réalisation des objectifs | I96: Moyenne
D97: Rapports de réalisation des objectifs délégués analysés | E97: Les rapports de réalisation des objectifs délégués ont-ils été analysés ? | F97: PAS | G97: Rapport de suivi des objectifs délégués, Rapport d'analyse des écarts | H97: Non-atteinte des objectifs délégués sans mise en place d'actions correctives | I97: Moyenne
D98: Actions correctives mises en œuvre en cas d’objectifs non atteints documentées | E98: Des actions correctives en cas d’objectifs non atteints ont-elles été documentées ? | F98: PAS | G98: Document des actions correctives mises en œuvre, Rapport d'évaluation des actions | H98: Absence de suivi des actions correctives, entraînant des retards ou erreurs répétées | I98: Moyenne
D99: Feedback des instances sur l’efficacité des délégations recueilli | E99: Le feedback des instances sur l’efficacité des délégations a-t-il été recueilli ? | F99: PAS | G99: Feedback des instances de pilotage, Document de synthèse des retours | H99: Manque de retour sur l'efficacité des délégations, empêchant l'amélioration continue | I99: Moyenne
D100: Évolution des responsabilités déléguées en fonction des performances validée | E100: L’évolution des responsabilités déléguées en fonction des performances a-t-elle été validée ? | F100: PAS | G100: Document d'évaluation des évolutions de responsabilités, Rapport de validation des performances | H100: Retards dans l'adaptation des responsabilités en fonction des performances | I100: Moyenne
...

Sheet 4.4
A1: Domaines | B1: Points de Contrôle | C1: Objectifs de contrôle | D1: Critères d’évaluation | E1: Question d’Évaluation | F1: Réponses | G1: Documents Requis | H1: Risques | I1: Criticité | J1: Conséquences | K1: Recommandations
A2: SUPPORT UTILISATEUR ET GESTON DU PARC | B2: Fonction support : audit fiabilité et sécurité | C2: S’assurer qu’une structure de centre d’assistance (help-desk) (HD) est mise en place | D2: Existence d’une organisation dédiée avec des ressources identifiées | E2: Existe-t-il une organisation dédiée avec des ressources identifiées ? | F2: OUI | G2: Organigramme du centre d'assistance, Plan de gestion des ressources humaines du HD | H2: Absence de cadre organisationnel structuré | I2: Elevée | J2: Délais de traitement allongés et insatisfaction des utilisateurs | K2: Élaborer un organigramme fonctionnel avec fiches de poste détaillées
D3: Nomination d’un responsable du centre d’assistance | E3: Un responsable du centre d’assistance a-t-il été nommé ? | F3: NON | G3: Acte de nomination du responsable du centre d’assistance, Description de poste du responsable du centre d’assistance | H3: Dilution des responsabilités opérationnelles | I3: Moyenne | J3: Confusion dans l'exécution des tâches critiques | K3: Établir une matrice RACI pour chaque processus clé
D4: Disponibilité d’un budget dédié au fonctionnement du HD | E4: Un budget spécifique est-il alloué au fonctionnement du HD ? | F4: OUI | G4: Budget annuel alloué au fonctionnement du HD, Plan de financement et prévisions budgétaires pour le HD | H4: Insuffisance budgétaire chronique | I4: Faible | J4: Dégradation progressive de la qualité de service | K4: Mettre en place une budgétisation basée sur les besoins réels
D5: Existence d’un local ou espace identifié pour le HD | E5: Un local ou un espace est-il identifié pour le HD ? | F5: OUI | G5: Plan d’aménagement des espaces du centre d’assistance, Contrat de location ou de mise à disposition des locaux | H5: Dispersion géographique des équipes | I5: Moyenne | J5: Inefficacité dans la coordination des interventions | K5: Déployer des outils collaboratifs unifiés et standardisés
D6: Niveau de service défini et formalisé | E6: Un niveau de service est-il défini et formalisé ? | F6: OUI | G6: Document de définition des niveaux de service (SLA), Accord de niveau de service signé avec les parties prenantes | H6: Définition floue des engagements de service | I6: Faible | J6: Attentes divergentes entre parties prenantes | K6: Formaliser un SLA avec indicateurs mesurables et validés
C7: S’assurer qu’une procédure de gestion des demandes d’assistance est diffusée et connue des utilisateurs | D7: Existence d’un document formalisé de procédure | E7: Un document de procédure est-il formalisé ? | F7: OUI | G7: Manuel des procédures opérationnelles du HD, Document de procédures d'assistance utilisateur | H7: Improvisation des processus de support | I7: Elevée | J7: Incohérence dans les traitements des demandes | K7: Documenter les procédures dans un référentiel unique
D8: Communication de la procédure à tous les utilisateurs | E8: La procédure est-elle communiquée à tous les utilisateurs ? | F8: NON | G8: Email de communication de la procédure aux utilisateurs, Affiche ou notice informant les utilisateurs de la procédure | H8: Méconnaissance des procédures par les utilisateurs | I8: Moyenne | J8: Non-respect systématique des processus | K8: Lancer des campagnes de sensibilisation ciblées
D9: Accessibilité de la procédure via l’intranet ou support papier | E9: La procédure est-elle accessible via l’intranet ou un support papier ? | F9: OUI | G9: Page intranet dédiée aux procédures du HD, Brochure papier des procédures du centre d’assistance | H9: Difficulté d'accès aux référentiels | I9: Elevée | J9: Difficultés à trouver l'information nécessaire | K9: Centraliser les documents dans un portail unique et intuitif
D10: Mises à jour régulières du document | E10: Le document de procédure est-il mis à jour régulièrement ? | F10: PAS | G10: Registre des versions du document de procédure, Rapport de révision annuelle des procédures | H10: Application de procédures obsolètes | I10: Elevée | J10: Application de méthodes inadaptées | K10: Instaurer des revues trimestrielles des processus
D11: Validation de la procédure par la DSI | E11: La procédure a-t-elle été validée par la DSI ? | F11: OUI | G11: Document de validation de la procédure par la DSI, Compte-rendu de la réunion de validation avec la DSI | H11: Désalignement avec la stratégie SI | I11: Elevée | J11: Conflits opérationnels récurrents | K11: Aligner les procédures avec la roadmap SI
C12: S’assurer qu’une procédure d'escalade mise en place | D12: Formalisme de la procédure d’escalade | E12: La procédure d’escalade est-elle formalisée ? | F12: PAS | G12: Document décrivant les étapes d’escalade des incidents, Schéma de procédure d’escalade avec les rôles et responsabilités | H12: Gestion réactive des urgences | I12: Elevée | J12: Aggravation des incidents critiques | K12: Formaliser des procédures d'urgence avec seuils d'activation
D13: Existence de paliers définis et rôles associés | E13: Des paliers d’escalade et les rôles associés sont-ils définis ? | F13: OUI | G13: Tableau récapitulatif des paliers d’escalade et des rôles associés, Description des responsabilités et actions à chaque palier d’escalade | H13: Flou dans la chaîne d'escalade | I13: Elevée | J13: Escalades inappropriées ou tardives | K13: Définir clairement les paliers et responsabilités
D14: Temps de réponse par niveau d’escalade | E14: Un temps de réponse est-il prévu pour chaque niveau d’escalade ? | F14: OUI | G14: Accord de niveau de service (SLA) avec les temps de réponse, Tableau de suivi des temps de réponse par niveau d’escalade | H14: Dépassement systématique des délais | I14: Elevée | J14: Détérioration de la relation utilisateur | K14: Implémenter des outils de suivi des délais avec alertes
D15: Formation des équipes sur les règles d’escalade | E15: Les équipes sont-elles formées aux règles d’escalade ? | F15: OUI | G15: Plan de formation sur les procédures d’escalade, Fiches de formation sur les niveaux d’escalade et les procédures associées | H15: Incompétence technique sur les incidents complexes | I15: Faible | J15: Non-résolution des problèmes complexes | K15: Créer un référentiel de connaissances techniques
D16: Suivi des escalades enregistrées | E16: Les escalades sont-elles suivies et enregistrées ? | F16: PAS | G16: Tableau de bord des escalades avec dates et statuts, Rapport d'analyse des escalades enregistrées | H16: Couverture inégale des sites distants | I16: Faible | J16: Inégalité de service entre sites | K16: Établir des standards minimums par site
C17: S’assurer de la couverture géographique du HD | D17: Liste des sites couverts par le HD | E17: Une liste des sites couverts par le HD est-elle disponible ? | F17: OUI | G17: Document listant les sites géographiques couverts par le HD, Carte des sites couverts par le centre d’assistance | H17: Déséquilibre des ressources par site | I17: Elevée | J17: Surcharge des équipes sur certains sites | K17: Mettre en place un système de mutualisation des ressources
D18: Disponibilité d’un support pour chaque site | E18: Un support est-il disponible pour chaque site ? | F18: OUI | G18: Plan de support par site, avec les horaires et contacts, Document de répartition des agents par site et par zone géographique | H18: Inadéquation des outils de télésupport | I18: Moyenne | J18: Prise en charge dégradée à distance | K18: Investir dans des outils de télémaintenance performants
D19: Analyse des besoins selon les localisations | E19: Une analyse des besoins est-elle effectuée selon les localisations ? | F19: OUI | G19: Rapport d’analyse des besoins spécifiques par localisation, Enquête de satisfaction locale sur les services d’assistance | H19: Disparité de qualité entre sites | I19: Moyenne | J19: Perception négative du service global | K19: Harmoniser les processus qualité entre sites
D20: Outils permettant une prise en charge à distance | E20: Des outils permettent-ils une prise en charge à distance ? | F20: OUI | G20: Manuel d’utilisation des outils de prise en charge à distance, Politique de sécurité pour l’utilisation des outils de prise en charge à distance | H20: Limitation arbitraire des demandes traitables | I20: Moyenne | J20: Frustration des utilisateurs | K20: Publier un catalogue des services accessibles
D21: Niveau de satisfaction par site | E21: Le niveau de satisfaction est-il évalué pour chaque site ? | F21: NON | G21: Rapport de satisfaction des utilisateurs par site, Enquête de satisfaction utilisateur par site | H21: Fenêtres de support trop restrictives | I21: Moyenne | J21: Besoins non couverts en horaires décalés | K21: Étudier un système d'astreintes ou de relais
C22: S’assurer de la couverture fonctionnelle du HD | D22: Nombre de types de demandes pris en charge | E22: Les différents types de demandes pris en charge sont-ils répertoriés ? | F22: OUI | G22: Catalogue des types de demandes supportées, Fiche d’inventaire des demandes selon leur typologie | H22: Expertises thématiques mal réparties | I22: Moyenne | J22: Surcharge des experts spécialisés | K22: Cartographier les compétences et rééquilibrer les effectifs
D23: Couverture des plages horaires d’assistance | E23: Les plages horaires d’assistance couvrent-elles tous les besoins ? | F23: OUI | G23: Planning des horaires d’assistance du centre, Document de gestion des horaires et des ressources | H23: Taux de résolution insatisfaisant | I23: Moyenne | J23: Insatisfaction client persistante | K23: Analyser les causes racines des non-résolutions
D24: Spécialisation des agents selon les thématiques | E24: Les agents sont-ils spécialisés selon les thématiques ? | F24: OUI | G24: Organigramme des agents spécialisés selon les thématiques, Fiche de spécialisation des agents par domaine d’assistance | H24: Offre de services non formalisée | I24: Moyenne | J24: Demandes hors périmètre non traitées | K24: Diffuser largement le catalogue de services
D25: Taux de résolution par type de demande | E25: Le taux de résolution est-il mesuré par type de demande ? | F25: OUI | G25: Rapport de suivi du taux de résolution par type de demande, Tableau récapitulatif des résolutions par catégorie de demande | H25: Hétérogénéité des outils utilisés | I25: Elevée | J25: Difficultés d'interopérabilité | K25: Standardiser les outils sur une plateforme unique
D26: Existence d’un catalogue de services supportés | E26: Un catalogue des services supportés existe-t-il ? | F26: OUI | G26: Catalogue de services et demandes supportées par le centre d’assistance, Brochure de présentation des services du HD | H26: Fonctionnalités critiques manquantes | I26: Moyenne | J26: Incapacité à traiter certains types de demandes | K26: Auditer les fonctionnalités manquantes prioritairement
C27: S’assurer qu’un outil est implémenté pour la prise d'appel et le suivi des tickets | D27: Outil référencé et déployé dans tous les services | E27: Un outil de gestion des tickets est-il référencé et déployé dans tous les services ? | F27: PAS | G27: Rapport de déploiement des outils dans les différents services, Manuel de l’outil de gestion de tickets et de support | H27: Isolement du système de ticketing | I27: Moyenne | J27: Isolement des données utiles | K27: Développer des API d'intégration
D28: Fonctionnalités de gestion de tickets disponibles | E28: Les fonctionnalités de gestion de tickets sont-elles disponibles ? | F28: OUI | G28: Document technique sur les fonctionnalités de gestion de tickets, Guide utilisateur sur la gestion des tickets d’assistance | H28: Dérives dans les délais de traitement | I28: Elevée | J28: Dérives temporelles non détectées | K28: Automatiser le suivi des délais avec reporting
D29: Intégration avec les autres outils SI | E29: L’outil est-il intégré aux autres outils du système d'information ? | F29: OUI | G29: Plan d’intégration de l’outil d’assistance avec d’autres outils SI, Rapport de validation de l’intégration des outils SI | H29: Sous-utilisation des capacités outils | I29: Moyenne | J29: Sous-exploitation des fonctionnalités | K29: Former les équipes aux capacités avancées
D30: Suivi des délais de traitement | E30: Le délai de traitement des tickets est-il suivi ? | F30: OUI | G30: Rapport de suivi des délais de traitement des demandes, Tableau de bord des délais de traitement par type de demande | H30: Critères de qualification inadaptés | I30: Moyenne | J30: Mauvais aiguillage des demandes | K30: Réviser les critères avec les équipes terrain
D31: Taux d’utilisation par les agents | E31: Le taux d’utilisation de l’outil par les agents est-il mesuré ? | F31: OUI | G31: Rapport d’utilisation des outils par les agents, Analyse des performances et taux d’utilisation des agents | H31: Écart entre théorie et réalité terrain | I31: Elevée | J31: Écart entre procédures et pratique | K31: Organiser des ateliers de remontée terrain
C32: S’assurer que des critères à renseigner pour la qualification des tickets existent | D32: Liste des critères de qualification disponible | E32: Une liste des critères de qualification est-elle disponible ? | F32: PAS | G32: Document listant les critères de qualification des tickets, Manuel de qualification des tickets d’assistance | H32: Mauvaise catégorisation des tickets | I32: Elevée | J32: Statistiques faussées | K32: Former à la qualification et auditer régulièrement
D33: Cohérence des critères avec les incidents rencontrés | E33: Ces critères sont-ils cohérents avec les incidents rencontrés ? | F33: OUI | G33: Rapport d’évaluation de la cohérence des critères de qualification, Analyse des incidents qualifiés selon les critères | H33: Qualification erronée des demandes | I33: Faible | J33: Décisions basées sur des mauvais critères | K33: Actualiser les arbres de décision
D34: Formation à la qualification des tickets | E34: Les équipes sont-elles formées à la qualification des tickets ? | F34: OUI | G34: Programme de formation à la qualification des tickets, Guide de bonnes pratiques pour la qualification des tickets | H34: Critères de tri obsolètes | I34: Faible | J34: Saisie incomplète ou erronée | K34: Implémenter des aides contextuelles obligatoires
D35: Taux de tickets correctement qualifiés | E35: Le taux de tickets correctement qualifiés est-il mesuré ? | F35: OUI | G35: Rapport mensuel sur le taux de tickets correctement qualifiés, Suivi des tickets avec des erreurs de qualification | H35: Saisie sans guidage approprié | I35: Faible | J35: Difficulté à renseigner les champs | K35: Simplifier et documenter chaque champ
D36: Revue périodique des critères de qualification | E36: Les critères de qualification font-ils l’objet d’une revue périodique ? | F36: OUI | G36: Rapport de revue périodique des critères de qualification, Document de révision des critères de qualification | H36: Champs mal configurés ou ambigus | I36: Faible | J36: Impossibilité d'accéder à l'aide | K36: Garantir une documentation toujours accessible
B37: Fonction support : audit d'efficacité et de performance | C37: S’assurer qu’il existe une aide à la saisie pour la saisie des tickets | D37: Existence d’une aide contextuelle à la saisie | E37: Une aide contextuelle à la saisie est-elle disponible ? | F37: PAS | G37: Document expliquant l’aide contextuelle à la saisie des tickets, Capture d'écran ou description de l’interface avec l’aide contextuelle | H37: Support d'aide inaccessible | I37: Faible | J37: Persistance des difficultés utilisateurs | K37: Tester l'efficacité des aides avec des focus groups
D38: Présence de champs obligatoires et info-bulles | E38: Des champs obligatoires et des info-bulles sont-ils présents dans les formulaires ? | F38: PAS | G38: Manuel utilisateur sur les champs obligatoires dans les formulaires, Document de spécification fonctionnelle des champs et info-bulles | H38: Inefficacité des aides contextuelles | I38: Faible | J38: Recours excessif aux équipes | K38: Améliorer l'ergonomie des outils d'auto-assistance
D39: Accessibilité de l’aide en ligne ou support physique | E39: L’aide en ligne ou le support physique est-il facilement accessible ? | F39: PAS | G39: Guide d’accès à l’aide en ligne du centre d’assistance, Catalogue du support physique et de l’assistance sur site | H39: Accès limité aux ressources d'assistance | I39: Faible | J39: Faible utilisation des ressources disponibles | K39: Former systématiquement aux outils d'aide
D40: Évaluation de l’efficacité de l’aide par les utilisateurs | E40: L’efficacité de l’aide est-elle évaluée par les utilisateurs ? | F40: PAS | G40: Rapport d'évaluation de l'efficacité de l'aide, Enquête de satisfaction sur l'efficacité de l'aide | H40: Faible adoption des outils d'aide par les utilisateurs | I40: Faible | J40: Documentation technique obsolète | K40: Nommer un responsable des mises à jour documentaires
D41: Mise à jour régulière du support d’aide | E41: Le support d’aide est-il mis à jour régulièrement ? | F41: PAS | G41: Rapport de mise à jour du support d’aide, Plan de mise à jour du support d’aide | H41: Support technique obsolète ou incomplet | I41: Moyenne | J41: Qualité inégale des services | K41: Instaurer des revues qualité trimestrielles
C42: S’assurer qu’il existe des revues qualité pour la saisie des tickets | D42: Existence d’un calendrier de revue qualité formalisé | E42: Un calendrier de revue qualité est-il formalisé ? | F42: PAS | G42: Document de planification des revues qualité, Calendrier annuel des revues qualité | H42: Absence de processus structuré d'amélioration qualité | I42: Moyenne | J42: Non-traçabilité des améliorations | K42: Documenter systématiquement les revues
D43: Présence de comptes-rendus documentés des revues qualité | E43: Des comptes-rendus documentés des revues qualité sont-ils disponibles ? | F43: OUI | G43: Compte-rendu de revue qualité, Synthèse des résultats des revues qualité | H43: Défaut de traçabilité des revues qualité | I43: Moyenne | J43: Persistance des problèmes connus | K43: Prioriser les actions correctives
D44: Analyse des écarts et recommandations issues des revues | E44: Les écarts constatés lors des revues sont-ils analysés et donnent-ils lieu à des recommandations ? | F44: OUI | G44: Rapport d’analyse des écarts de qualité, Plan d'action basé sur les écarts relevés | H44: Non-respect des bonnes pratiques identifiées | I44: Moyenne | J44: Retard dans les corrections | K44: Automatiser le suivi des plans d'action
D45: Suivi des actions correctives engagées suite aux revues | E45: Les actions correctives issues des revues sont-elles suivies ? | F45: OUI | G45: Tableau de suivi des actions correctives, Rapport d’état d’avancement des actions correctives | H45: Retard dans la mise en œuvre des corrections | I45: Moyenne | J45: Démobilisation des équipes | K45: Associer les équipes aux processus d'amélioration
D46: Implication de l’équipe HD dans les revues qualité | E46: L’équipe HD est-elle impliquée dans les revues qualité ? | F46: OUI | G46: Compte-rendu des réunions avec l’équipe HD, Plan de participation de l’équipe HD aux revues qualité | H46: Démotivation des équipes face aux processus qualité | I46: Moyenne | J46: Prise de décision sans données | K46: Implémenter des enquêtes satisfaction obligatoires
C47: S’assurer que des études de satisfaction sont réalisées auprès des utilisateurs | D47: Existence d’un questionnaire de satisfaction utilisateur | E47: Un questionnaire de satisfaction utilisateur existe-t-il ? | F47: OUI | G47: Questionnaire de satisfaction utilisateur, Rapport d’analyse des réponses au questionnaire de satisfaction | H47: Données insuffisantes pour mesurer la satisfaction | I47: Elevée | J47: Biais d'évaluation | K47: Diversifier les canaux de collecte de feedback
D48: Taux de retour des enquêtes de satisfaction | E48: Le taux de retour des enquêtes de satisfaction est-il mesuré ? | F48: OUI | G48: Statistiques sur le taux de retour des enquêtes, Rapport sur le taux de réponse aux enquêtes | H48: Biais dans l'évaluation de la satisfaction client | I48: Moyenne | J48: Persistance des problèmes récurrents | K48: Analyser les tendances satisfaction mensuellement
D49: Analyse des résultats et des tendances de satisfaction | E49: Les résultats des enquêtes et les tendances de satisfaction sont-ils analysés ? | F49: OUI | G49: Rapport d’analyse des tendances de satisfaction, Présentation des résultats d'enquête sur la satisfaction | H49: Ignorance des problèmes récurrents | I49: Elevée | J49: Stagnation de la qualité de service | K49: Publier un plan d'amélioration visible
D50: Mise en œuvre d’un plan d’amélioration continue | E50: Un plan d’amélioration continue est-il mis en œuvre ? | F50: OUI | G50: Plan d’amélioration continue documenté, Rapport d'avancement du plan d’amélioration continue | H50: Immobilisme dans l'amélioration des services | I50: Elevée | J50: Opacité sur les performances | K50: Communiquer régulièrement les résultats
D51: Communication des résultats aux parties prenantes | E51: La communication des résultats aux parties prenantes a-t-elle été effectuée ? | F51: OUI | G51: Document de communication des résultats aux parties prenantes, Rapport de présentation des résultats aux parties prenantes | H51: Manque de transparence sur les performances | I51: Elevée | J51: Non-atteinte des standards | K51: Élaborer un plan de certification progressif
C52: S’assurer que l’obtention des certifications (ITIL, ISO, COBIT, SIGMA) est encouragée au sein de la DSI, et du HD en particulier | D52: Documentation des certifications visées par la DSI et le HD | E52: Les certifications visées par la DSI et le HD sont-elles documentées ? | F52: OUI | G52: Liste des certifications visées par la DSI, Dossier de présentation des démarches de certification | H52: Objectifs de certification non atteints | I52: Moyenne | J52: Non-conformité aux exigences | K52: Auditer régulièrement les écarts de certification
D53: Suivi des démarches de certification entreprises | E53: Les démarches de certification entreprises sont-elles suivies ? | F53: OUI | G53: Plan de suivi des démarches de certification, Tableau de bord des démarches de certification | H53: Non-conformité aux standards du secteur | I53: Moyenne | J53: Exposition à des sanctions réglementaires | K53: Mettre en place un registre des exigences légales avec rappels automatiques
D54: Accompagnement et financement des formations certifiantes | E54: L’accompagnement et le financement des formations certifiantes ont-ils été mis en place ? | F54: OUI | G54: Plan d’accompagnement et financement des formations, Budget de financement des formations certifiantes | H54: Désengagement dans le développement des compétences | I54: Moyenne | J54: Perte de compétitivité technologique | K54: Élaborer un plan de développement des compétences aligné sur la stratégie SI
D55: Mise en place d’une politique interne de valorisation des certifications | E55: Une politique interne de valorisation des certifications a-t-elle été instaurée ? | F55: OUI | G55: Document de politique interne de valorisation des certifications, Communication de la politique de valorisation des certifications | H55: Reconnaissance insuffisante des certifications | I55: Moyenne | J55: Démotivation des équipes techniques | K55: Créer un programme de valorisation des certifications obtenues
D56: Nombre de certifications obtenues par les équipes | E56: Le nombre de certifications obtenues par les équipes est-il suivi ? | F56: OUI | G56: Tableau récapitulatif des certifications obtenues, Rapport annuel des certifications obtenues | H56: Faible valorisation des expertises acquises | I56: Moyenne | J56: Sous-exploitation des expertises internes | K56: Implémenter un système de gestion des talents et compétences
C57: Vérifier la stratégie de formation des utilisateurs et de l’équipe Helpdesk | D57: Existence d’un plan de formation annuel validé | E57: Un plan de formation annuel validé existe-t-il ? | F57: OUI | G57: Plan de formation annuel validé, Rapport de validation du plan de formation annuel | H57: Plan de formation inadapté aux besoins réels | I57: Moyenne | J57: Inadéquation des compétences disponibles | K57: Réaliser une analyse annuelle des besoins en compétences
D58: Couverture des besoins des utilisateurs et du HD dans le plan | E58: Les besoins des utilisateurs et du HD sont-ils couverts dans le plan de formation ? | F58: OUI | G58: Analyse des besoins des utilisateurs dans le plan de formation, Document de couverture des besoins dans le plan | H58: Déséquilibre entre formation métier et technique | I58: Elevée | J58: Lacunes dans les savoir-faire critiques | K58: Équilibrer le plan de formation entre techniques et métiers
D59: Taux de participation aux formations programmées | E59: Le taux de participation aux formations programmées est-il évalué ? | F59: OUI | G59: Rapport sur le taux de participation aux formations, Statistiques de participation aux formations programmées | H59: Participation insuffisante aux formations | I59: Moyenne | J59: Faible retour sur investissement formation | K59: Rendre obligatoire les formations clés avec suivi de participation
D60: Évaluation des compétences post-formation | E60: Les compétences post-formation sont-elles évaluées ? | F60: OUI | G60: Fiche d’évaluation des compétences post-formation, Rapport de suivi des compétences post-formation | H60: Efficacité non mesurée des actions de formation | I60: Moyenne | J60: Incapacité à évaluer l'impact des formations | K60: Développer des indicateurs d'efficacité post-formation
D61: Suivi des formations obligatoires et des mises à jour | E61: Le suivi des formations obligatoires et des mises à jour est-il effectué ? | F61: OUI | G61: Liste des formations obligatoires, Rapport de suivi des mises à jour des formations obligatoires | H61: Non-respect des obligations réglementaires de formation | I61: Moyenne | J61: Vulnérabilité légale et opérationnelle | K61: Automatiser le suivi des formations obligatoires
B62: Gestion du parc matériel et logiciel : audit fiabilité et sécurité | C62: Vérifier la procédure de déploiement des mises à jour, d’un nouveau logiciel | D62: Procédure documentée de déploiement des mises à jour | E62: Une procédure documentée de déploiement des mises à jour existe-t-elle ? | F62: OUI | G62: Document de procédure de déploiement des mises à jour, Plan de déploiement des mises à jour | H62: Absence de méthodologie standardisée pour les mises à jour | I62: Faible | J62: Incohérences dans les déploiements | K62: Standardiser les procédures de mise à jour
D63: Rétroplanning des déploiements disponible | E63: Un rétroplanning des déploiements est-il disponible ? | F63: OUI | G63: Rétroplanning des déploiements, Calendrier des déploiements de mises à jour | H63: Délais de déploiement non maîtrisés | I63: Faible | J63: Retards dans les corrections de vulnérabilités | K63: Établir des rétroplannings contraignants avec jalons
D64: Validation technique avant déploiement généralisé | E64: La validation technique avant déploiement généralisé est-elle réalisée ? | F64: OUI | G64: Rapport de validation technique avant déploiement, Document de validation pré-déploiement | H64: Propagation d'erreurs techniques en production | I64: Elevée | J64: Instabilité des environnements de production | K64: Instaurer des environnements de pré-production stricts
D65: Suivi des anomalies post-déploiement | E65: Les anomalies post-déploiement sont-elles suivies ? | F65: OUI | G65: Rapport de suivi des anomalies post-déploiement, Tableau de gestion des anomalies après déploiement | H65: Augmentation du volume d'incidents post-déploiement | I65: Elevée | J65: Surcharge des équipes support | K65: Mettre en place un monitoring post-déploiement renforcé
D66: Communication aux utilisateurs avant et après déploiement | E66: La communication aux utilisateurs avant et après déploiement a-t-elle été effectuée ? | F66: PAS | G66: Document de communication avant déploiement, Compte-rendu de communication post-déploiement | H66: Manque d'information des utilisateurs impactés | I66: Moyenne | J66: Confusion et frustration des utilisateurs | K66: Développer un plan de communication pré/post déploiement
C67: Vérifier les outils mis en place pour gérer les versions des logiciels | D67: Existence d’un outil de gestion des versions référencé | E67: Un outil de gestion des versions référencé existe-t-il ? | F67: OUI | G67: Document référentiel de l’outil de gestion des versions, Liste des outils de gestion des versions utilisés | H67: Utilisation d'outils non homologués pour la gestion des versions | I67: Moyenne | J67: Risques de sécurité non maîtrisés | K67: Homologuer officiellement les outils de gestion de version
D68: Journal des versions et évolutions conservé | E68: Le journal des versions et évolutions est-il conservé ? | F68: PAS | G68: Journal des versions avec historique des évolutions, Rapport de mise à jour des versions et évolutions | H68: Perte de traçabilité des évolutions logicielles | I68: Moyenne | J68: Difficulté à diagnostiquer les régressions | K68: Maintenir un journal des versions avec suivi des changements
D69: Lien entre version et incidents remontés | E69: Le lien entre version et incidents remontés est-il établi ? | F69: OUI | G69: Tableau des versions liées aux incidents, Rapport d'analyse des incidents par version | H69: Non-correlation entre versions et problèmes rencontrés | I69: Moyenne | J69: Persistance de bugs non résolus | K69: Implémenter un système de traçabilité bugs/versions
D70: Possibilité de rollback des versions en cas de dysfonctionnement | E70: La possibilité de rollback des versions en cas de dysfonctionnement est-elle disponible ? | F70: PAS | G70: Procédure de rollback des versions, Plan d’action en cas de dysfonctionnement des versions | H70: Impossibilité de restauration en cas d'échec critique | I70: Moyenne | J70: Indisponibilités prolongées | K70: Prévoir systématiquement des mécanismes de rollback
D71: Utilisation d’indicateurs de stabilité par version | E71: Des indicateurs de stabilité par version sont-ils utilisés ? | F71: PAS | G71: Rapport d’analyse des indicateurs de stabilité par version, Tableau de bord des indicateurs de stabilité des versions | H71: Absence de mesure objective de la stabilité des versions | I71: Moyenne | J71: Décisions basées sur des données inexactes | K71: Développer des indicateurs de stabilité par version
C72: Vérifier les outils mis en place pour gérer le matériel informatique | D72: Outil d’inventaire du matériel utilisé et à jour | E72: Un outil d’inventaire du matériel utilisé et à jour est-il en place ? | F72: PAS | G72: Liste d'inventaire du matériel utilisé, Rapport d’audit du matériel utilisé | H72: Inventaire matériel incomplet ou obsolète | I72: Faible | J72: Surcoûts liés au sur-stockage ou pénuries | K72: Automatiser l'inventaire matériel avec scans réguliers
D73: Mise à jour régulière des fiches de vie des équipements | E73: Les fiches de vie des équipements sont-elles mises à jour régulièrement ? | F73: PAS | G73: Tableau de suivi des fiches de vie des équipements, Rapport de mise à jour des fiches de vie | H73: Fiches techniques non actualisées | I73: Elevée | J73: Erreurs dans les commandes de matériel | K73: Désigner un responsable des mises à jour techniques
D74: Affectation du matériel par utilisateur ou service | E74: Le matériel est-il affecté par utilisateur ou service ? | F74: PAS | G74: Registre d’affectation du matériel, Fiche d’affectation du matériel par service ou utilisateur | H74: Flou dans l'attribution des ressources matérielles | I74: Elevée | J74: Conflits d'attribution des ressources | K74: Implémenter un système de réservation centralisé
D75: Historique des incidents matériels associé à chaque équipement | E75: Un historique des incidents matériels associé à chaque équipement existe-t-il ? | F75: PAS | G75: Historique des incidents matériels associé à chaque équipement, Registre des incidents matériels par équipement | H75: Non-exploitation des historiques d'incidents matériels | I75: Moyenne | J75: Répétition des pannes matérielles | K75: Créer des fiches vie des équipements avec historique
D76: Indicateurs de rotation et vétusté du matériel | E76: Des indicateurs de rotation et de vétusté du matériel sont-ils suivis ? | F76: PAS | G76: Rapport de suivi des incidents matériels, Tableau des indicateurs de rotation et vétusté du matériel | H76: Surutilisation ou sous-utilisation des équipements | I76: Moyenne | J76: Dégradation prématurée du matériel | K76: Établir des indicateurs d'utilisation et seuils d'alerte
C77: S’assurer que l'installation des PC / portables est faite à partir d'un master (configuration minimum et standardisée) | D77: Procédure de création et utilisation du master documentée | E77: La procédure de création et d’utilisation du master est-elle documentée ? | F77: PAS | G77: Rapport d’analyse de la vétusté du matériel, Document de procédure de création du master | H77: Absence de référence standard pour les installations | I77: Faible | J77: Problèmes de compatibilité et stabilité | K77: Développer une image master de référence certifiée
D78: Standardisation des configurations applicables à tous les postes | E78: Les configurations applicables à tous les postes sont-elles standardisées ? | F78: PAS | G78: Manuel d’utilisation du master, Document de standardisation des configurations | H78: Hétérogénéité des configurations déployées | I78: Faible | J78: Complexité de gestion et support | K78: Standardiser les configurations via des outils de déploiement
D79: Mises à jour régulières du master | E79: Les mises à jour du master sont-elles régulières ? | F79: PAS | G79: Rapport de conformité des configurations, Plan de mise à jour du master | H79: Utilisation de masters obsolètes | I79: Faible | J79: Vulnérabilités de sécurité persistantes | K79: Établir un calendrier de mise à jour des masters
D80: Validation du master avant diffusion | E80: Le master est-il validé avant diffusion ? | F80: PAS | G80: Rapport de suivi des mises à jour du master, Rapport de validation du master | H80: Diffusion de configurations non validées | I80: Faible | J80: Instabilité des postes utilisateurs | K80: Valider systématiquement les images avant déploiement
D81: Taux de conformité des installations aux standards | E81: Le taux de conformité des installations aux standards est-il suivi ? | F81: PAS | G81: Document de procédure de validation du master, Rapport de conformité des installations aux standards | H81: Déviations importantes par rapport aux standards | I81: Faible | J81: Non-conformité aux politiques de sécurité | K81: Auditer régulièrement la conformité des postes
C82: S’assurer qu’il existe un processus spécifique pour le suivi des mises à jour sur les portables | D82: Suivi des mises à jour via outil ou référentiel dédié | E82: Les mises à jour sont-elles suivies via un outil ou référentiel dédié ? | F82: PAS | G82: Tableau de suivi des installations conformes, Rapport de suivi des mises à jour via outil | H82: Mauvaise visibilité sur l'état des mises à jour | I82: Faible | J82: Exposition aux cyber-risques | K82: Déployer un système centralisé de gestion des patches
D83: Alertes ou notifications sur les mises à jour critiques | E83: Des alertes ou notifications sur les mises à jour critiques sont-elles envoyées ? | F83: PAS | G83: Tableau de bord de suivi des mises à jour, Système d’alertes de mise à jour | H83: Retard dans l'application des correctifs critiques | I83: Elevée | J83: Exploitation de vulnérabilités connues | K83: Automatiser les alertes pour les mises à jour critiques
D84: Historique des mises à jour par équipement | E84: L’historique des mises à jour par équipement est-il conservé ? | F84: PAS | G84: Rapport d’analyse des notifications critiques, Journal des mises à jour par équipement | H84: Historique des patchs incomplet | I84: Elevée | J84: Difficulté à identifier les correctifs manquants | K84: Implémenter un système automatisé de suivi des patchs
D85: Rapports périodiques sur le taux de mise à jour | E85: Des rapports périodiques sur le taux de mise à jour sont-ils générés ? | F85: OUI | G85: Rapport d'historique des mises à jour, Rapport périodique sur le taux de mise à jour | H85: Taux de conformité non mesuré | I85: Elevée | J85: Incapacité à prouver la conformité | K85: Développer des tableaux de bord de conformité en temps réel
D86: Processus d’escalade en cas de non-conformité | E86: Un processus d’escalade en cas de non-conformité est-il en place ? | F86: OUI | G86: Tableau de bord des mises à jour, Document de procédure d’escalade | H86: Absence de processus de remédiation pour les non-conformités | I86: Elevée | J86: Persistance des vulnérabilités | K86: Établir des procédures de remédiation avec délais stricts
B87: Gestion du parc matériel et logiciel : audit d'efficacité et de performance | C87: Vérifier comment est effectué l'inventaire des licences (logiciel, version, date de mise en production, nombre d'utilisateurs) | D87: Inventaire centralisé des licences disponible | E87: Un inventaire centralisé des licences est-il disponible ? | F87: NON | G87: Plan d’action en cas de non-conformité, Rapport d’inventaire centralisé des licences | H87: Non-conformité aux obligations légales de licences | I87: Faible | J87: Amendes et sanctions légales | K87: Mettre en place un registre des obligations légales
D88: Mise à jour périodique de l’inventaire | E88: L’inventaire est-il mis à jour périodiquement ? | F88: OUI | G88: Liste des licences disponibles et en cours d’utilisation, Plan de mise à jour de l’inventaire | H88: Inventaire des licences obsolète ou incomplet | I88: Faible | J88: Audit défavorable et pénalités | K88: Automatiser les mises à jour de l'inventaire des licences
D89: Identification claire des logiciels, versions, dates et utilisateurs | E89: Les logiciels, versions, dates et utilisateurs sont-ils clairement identifiés ? | F89: PAS | G89: Tableau de suivi des mises à jour de l’inventaire, Registre des utilisateurs et des logiciels associés | H89: Impossibilité de tracer les utilisations réelles des logiciels | I89: Elevée | J89: Optimisation impossible des coûts | K89: Déployer des outils de monitoring des utilisations réelles
D90: Vérification des licences en fonction des besoins réels | E90: La vérification des licences en fonction des besoins réels est-elle effectuée ? | F90: OUI | G90: Tableau des logiciels et versions, Rapport de vérification des licences par besoin | H90: Sur-licensing ou sous-licensing coûteux | I90: Moyenne | J90: Dépenses inutiles ou risques légaux | K90: Réaliser des analyses régulières d'adéquation besoins/licences
D91: Outil automatisé ou procédure fiable d’inventaire utilisée | E91: Un outil automatisé ou une procédure fiable d’inventaire est-il utilisé ? | F91: PAS | G91: Analyse des licences en fonction des besoins réels, Documentation de l’outil d’inventaire automatisé | H91: Collecte manuelle et erreurs dans l'inventaire | I91: Elevée | J91: Erreurs dans la gestion des actifs | K91: Standardiser la collecte via des outils dédiés
C92: S’assurer que les outils de type SAM (Software Asset Management) sont déployés | D92: Existence d’un outil SAM officiellement déployé | E92: Un outil SAM officiellement déployé existe-t-il ? | F92: OUI | G92: Plan de gestion des inventaires automatisés, Document de déploiement de l’outil SAM | H92: Absence de solution professionnelle de gestion des licences | I92: Moyenne | J92: Gestion inefficace des licences | K92: Acquérir une solution SAM professionnelle
D93: Mise à jour régulière des données dans l’outil SAM | E93: Les données dans l’outil SAM sont-elles mises à jour régulièrement ? | F93: OUI | G93: Rapport de mise en place de l’outil SAM, Plan de mise à jour des données dans l’outil SAM | H93: Données SAM non fiables ou obsolètes | I93: Moyenne | J93: Décisions basées sur des données erronées | K93: Programmer des contrôles qualité des données SAM
D94: Capacité de l’outil à détecter les écarts entre usage et licences | E94: La capacité de l’outil à détecter les écarts entre usage et licences est-elle suffisante ? | F94: OUI | G94: Rapport de suivi des données dans l’outil SAM, Rapport de détection des écarts entre usage et licences | H94: Détection tardive des écarts de licence | I94: Moyenne | J94: Découverte tardive des non-conformités | K94: Configurer des alertes automatiques sur les écarts
D95: Interfaçage de l’outil SAM avec les systèmes d’information | E95: L’interfaçage de l’outil SAM avec les systèmes d’information a-t-il été réalisé ? | F95: PAS | G95: Analyse des écarts générée par l'outil SAM, Document d’interfaçage de l’outil SAM | H95: Silos d'information et données non consolidées | I95: Moyenne | J95: Vision fragmentée du patrimoine logiciel | K95: Intégrer le SAM avec les autres systèmes d'information
D96: Formation des équipes à l’utilisation de l’outil SAM | E96: Les équipes ont-elles été formées à l’utilisation de l’outil SAM ? | F96: OUI | G96: Rapport d’intégration avec les systèmes d’information, Plan de formation sur l’outil SAM | H96: Incompétence des équipes sur l'outil SAM | I96: Elevée | J96: Mauvaise utilisation des outils | K96: Former les équipes aux fonctionnalités avancées du SAM
C97: S’assurer qu’il existe des revues régulières des licences | D97: Planification régulière des revues de licences | E97: La planification régulière des revues de licences est-elle effectuée ? | F97: OUI | G97: Rapport de formation des équipes sur l’utilisation de l'outil SAM, Calendrier des revues de licences | H97: Revues de licences irrégulières ou absentes | I97: Elevée | J97: Contrôle insuffisant des licences | K97: Planifier des revues trimestrielles obligatoires
D98: Compte-rendu formalisé des revues de licences | E98: Les revues de licences font-elles l’objet d’un compte-rendu formalisé ? | F98: OUI | G98: Plan de suivi des revues de licences, Compte-rendu des revues de licences | H98: Absence de formalisation des constats et actions | I98: Elevée | J98: Absence de suivi des actions | K98: Documenter systématiquement les comptes-rendus de revue
D99: Analyse des écarts constatés et plans d’action associés | E99: Les écarts constatés lors des revues sont-ils analysés et des plans d’action associés sont-ils mis en place ? | F99: OUI | G99: Rapport de synthèse des résultats des revues, Rapport d’analyse des écarts | H99: Défaut d'analyse des écarts de conformité | I99: Moyenne | J99: Causes racines non identifiées | K99: Appliquer une méthodologie d'analyse des écarts
D100: Suivi des recommandations issues des revues | E100: Le suivi des recommandations issues des revues est-il assuré ? | F100: NON | G100: Plan d’action correctif suite aux écarts, Tableau de suivi des recommandations des revues | H100: Non suivi des plans de régularisation | I100: Elevée | J100: Non-résolution des problèmes | K100: Assigner des responsables pour chaque plan d'action
...

Sheet 4.5
A1: Domaines | B1: Points de Contrôle | C1: Objectifs de contrôle | D1: Critères d’évaluation | E1: Question d’Évaluation | F1: Réponses | G1: Documents Requis | H1: Risques | I1: Criticité | J1: Conséquences | K1: Recommandations
A2: SECURITE INFORMATIQUE | B2: Facteurs clés de succès | C2: Vérifier qu’une politique de sécurité est définie et correspond à l'activité de l'Organisation | D2: Existence d’un document officiel de politique de sécurité validé par la direction | E2: Existe-t-il un document officiel de politique de sécurité validé par la direction ? | F2: PAS | G2: Politique de classification des données, Référentiel de classification des actifs | H2: Non-respect des orientations stratégiques en matière de sécurité | I2: Elevée | J2: Détérioration de la posture sécurité globale et augmentation des vulnérabilités | K2: Mettre en place un comité de pilotage sécurité aligné avec la direction générale
D3: Cohérence entre les objectifs de la politique et les enjeux métiers spécifiques | E3: Les objectifs de la politique sont-ils cohérents avec les enjeux métiers spécifiques ? | F3: PAS | G3: Guide d'utilisation des données sensibles, Matrice d'accès aux données | H3: Défaut d’alignement entre la sécurité et les priorités métiers, entraînant des conflits ou des blocages | I3: Moyenne | J3: Rejet des mesures sécurité perçues comme des obstacles | K3: Intégrer des représentants métiers dans les décisions sécurité
D4: Mise à jour régulière de la politique en fonction de l’évolution des risques | E4: La politique est-elle mise à jour régulièrement en fonction de l'évolution des risques ? | F4: PAS | G4: Logiciel de gestion des actifs et des risques, Tableau de bord des indicateurs de sécurité | H4: Sous-estimation des menaces émergentes pouvant causer des incidents non anticipés | I4: Faible | J4: Incidents non couverts par les dispositifs existants | K4: Abonnement à des services de veille threat intelligence
D5: Prise en compte des obligations réglementaires et normatives dans la politique | E5: Les obligations réglementaires et normatives sont-elles prises en compte dans la politique ? | F5: PAS | G5: Rapport d'analyse d'impact sur la vie privée (AIP), Rapport d'analyse de risques métiers | H5: Exposition à des sanctions juridiques en cas de contrôle ou d’audit externe | I5: Moyenne | J5: Amendes et atteinte à la réputation | K5: Audit de conformité trimestriel avec cabinet externe
D6: Accessibilité de la politique à l’ensemble du personnel et des parties prenantes | E6: La politique est-elle accessible à l'ensemble du personnel et des parties prenantes ? | F6: PAS | G6: Registre des décisions de classification, Politique d'archivage des données | H6: Mésinformation ou incompréhension des obligations par les parties concernées | I6: Faible | J6: Application incohérente des mesures de sécurité | K6: Créer un portail unique d'information sécurité accessible à tous
C7: Vérifier qu’une démarche de mise en œuvre de la gestion de la sécurité est adoptée et compatible avec la culture de l'Organisation | D7: Présence d’un plan de gouvernance de la sécurité avec des rôles définis | E7: Existe-t-il un plan de gouvernance de la sécurité avec des rôles définis ? | F7: PAS | G7: Procédure de classification des données, Guide méthodologique pour l'évaluation des risques | H7: Manque de coordination entre les acteurs, générant des zones de responsabilité floues | I7: Elevée | J7: Chevauchement des responsabilités et inefficacité opérationnelle | K7: Élaborer une matrice RACI claire pour tous les processus sécurité
D8: Adéquation entre les pratiques de sécurité et les usages opérationnels de l’entreprise | E8: Les pratiques de sécurité sont-elles adéquates aux usages opérationnels de l'entreprise ? | F8: PAS | G8: Journal des modifications des actifs, Système de gestion des incidents et des problèmes | H8: Adoption de comportements ou outils non sécurisés par les utilisateurs | I8: Moyenne | J8: Augmentation des vecteurs d'attaque internes | K8: Déployer des solutions techniques de prévention avec monitoring comportemental
D9: Intégration des actions de sécurité dans les processus métiers existants | E9: Les actions de sécurité sont-elles intégrées dans les processus métiers existants ? | F9: PAS | G9: Rapport d'audit de conformité RGPD, Rapport d'audit de sécurité des systèmes d'information (SSI) | H9: Détournement des processus métiers pour contourner des mesures de sécurité jugées inadaptées | I9: Elevée | J9: Création de failles de sécurité involontaires | K9: Impliquer les utilisateurs dans la conception des mesures sécurité
D10: Niveau d’appropriation des mesures de sécurité par les équipes opérationnelles | E10: Le niveau d'appropriation des mesures de sécurité par les équipes opérationnelles est-il suffisant ? | F10: PAS | G10: Organigramme fonctionnel, Fiches de poste détaillées | H10: Contournement des procédures ou désengagement dans leur application | I10: Elevée | J10: Non-respect des politiques malgré leur existence | K10: Mettre en place des indicateurs de suivi et audits surprises
D11: Existence d’une évaluation d’impact culturel de la démarche de sécurité | E11: Une évaluation d'impact culturel de la démarche de sécurité a-t-elle été réalisée ? | F11: NON | G11: Référentiel des emplois et des compétences, Plan de formation individualisé | H11: Refus ou résistance passive face aux nouvelles exigences de sécurité | I11: Faible | J11: Retard dans l'implémentation des mesures critiques | K11: Instaurer un système de reporting mensuel à la direction
C12: Vérifier que la direction assure un soutien total et un engagement visible pour la sécurité | D12: Communication régulière de la direction sur les enjeux de sécurité | E12: La direction communique-t-elle régulièrement sur les enjeux de sécurité ? | F12: NON | G12: Tableau de suivi des équipements informatiques, Procédure de gestion des accès et des habilitations | H12: Perception faible des enjeux par les collaborateurs, entraînant un manque de vigilance | I12: Moyenne | J12: Manque de vigilance face aux attaques courantes | K12: Programme de sensibilisation continu avec simulations régulières
D13: Présence de la direction dans les comités de sécurité de l’information | E13: La direction est-elle présente dans les comités de sécurité de l'information ? | F13: OUI | G13: Contrat de location de matériel informatique, Licence d'utilisation de logiciel | H13: Décisions stratégiques prises sans considération des enjeux de cybersécurité | I13: Elevée | J13: Décisions exposant inutilement l'organisation | K13: Obligation de validation sécurité pour tout projet stratégique
D14: Allocation de ressources humaines et financières dédiées à la sécurité | E14: Des ressources humaines et financières sont-elles allouées à la sécurité ? | F14: OUI | G14: Plan d'allocation des ressources par projet, Tableau de suivi des effectifs par service | H14: Insuffisance de personnel qualifié ou de moyens techniques pour implémenter les mesures | I14: Elevée | J14: Impossibilité de mettre en œuvre des contrôles essentiels | K14: Plan de recrutement et formation pluriannuel en compétences sécurité
D15: Validation systématique par la direction des politiques et plans de sécurité | E15: La direction valide-t-elle systématiquement les politiques et plans de sécurité ? | F15: NON | G15: Plan de formation annuel, Catalogue de formations disponibles | H15: Retard ou absence d’application des mesures critiques validées | I15: Faible | J15: Persistance de vulnérabilités connues | K15: Système de ticketing avec escalade automatique après délai
D16: Implication de la direction dans la réponse aux incidents majeurs | E16: La direction est-elle impliquée dans la réponse aux incidents majeurs ? | F16: NON | G16: Matrice de compétences par métier, Plan de développement des compétences | H16: Manque d’efficacité dans la coordination lors des crises ou cyberattaques | I16: Faible | J16: Gestion inefficace des incidents majeurs | K16: Exercices de crise trimestriels avec scénarios réalistes
C17: Vérifier que les exigences de sécurité et les risques sont compris et évalués | D17: Réalisation périodique d’analyses de risques documentées | E17: Des analyses de risques documentées sont-elles réalisées périodiquement ? | F17: NON | G17: Calendrier des formations, Budget prévisionnel des formations | H17: Identification tardive des vulnérabilités critiques du système d’information | I17: Elevée | J17: Découverte tardive de failles exploitables | K17: Programme de bug bounty et scans continus
D18: Implication des responsables métiers dans l’identification des risques | E18: Les responsables métiers sont-ils impliqués dans l'identification des risques ? | F18: NON | G18: Veille réglementaire, Procédure de mise à jour des formations | H18: Mauvaise priorisation des investissements liés à la cybersécurité | I18: Moyenne | J18: Investissements sécurité non optimisés | K18: Modèle de calcul ROI sécurité pour prioriser les budgets
D19: Définition claire des exigences de sécurité dans les projets | E19: Les exigences de sécurité sont-elles définies clairement dans les projets ? | F19: NON | G19: Plan de financement des formations, Rapport de suivi des dépenses de formation | H19: Manque d’exigences sécuritaires dès la conception des projets informatiques | I19: Moyenne | J19: Failles architecturales difficiles à corriger | K19: Intégration systématique d'un architecte sécurité dans les projets
D20: Traçabilité des mesures de traitement des risques dans un plan d’action | E20: Les mesures de traitement des risques sont-elles traçables dans un plan d'action ? | F20: NON | G20: Référentiel des compétences par poste, Bilan des compétences individuelles | H20: Absence de suivi des mesures de remédiation, maintenant les failles existantes | I20: Moyenne | J20: Persistance des mêmes vulnérabilités année après année | K20: Tableau de bord de suivi des corrections avec responsables nommés
D21: Outils et méthodes utilisés pour l’évaluation des risques validés par la DSI | E21: Les outils et méthodes utilisés pour l'évaluation des risques sont-ils validés par la DSI ? | F21: NON | G21: Catalogue de formations par niveau hiérarchique, Parcours de formation personnalisés | H21: Usage d’outils non reconnus ou inadaptés, limitant la fiabilité des analyses | I21: Moyenne | J21: Analyses de sécurité peu fiables | K21: Standardisation des outils approuvés avec procédures de validation
C22: Vérifier que l’ensemble des responsables et des employés sont sensibilisés et informés | D22: Campagnes annuelles de sensibilisation à la sécurité de l’information | E22: Des campagnes annuelles de sensibilisation à la sécurité de l'information sont-elles organisées ? | F22: PAS | G22: Tests de positionnement, Entretiens individuels | H22: Persistance de comportements à risque en raison d’un manque de sensibilisation | I22: Moyenne | J22: Répétition des mêmes erreurs humaines | K22: Campagnes de sensibilisation ciblées par métier
D23: Taux de participation aux sessions de sensibilisation et de formation | E23: Le taux de participation aux sessions de sensibilisation et de formation est-il satisfaisant ? | F23: PAS | G23: Questionnaire de satisfaction des formations, Entretiens de suivi des formations | H23: Faible taux de couverture des actions de sensibilisation, augmentant la surface d’attaque | I23: Moyenne | J23: Surface d'attaque humaine étendue | K23: Mesurer le taux de participation obligatoire aux formations
D24: Diffusion de supports pédagogiques adaptés aux profils métiers | E24: Des supports pédagogiques adaptés aux profils métiers sont-ils diffusés ? | F24: PAS | G24: Programme de formation RGPD pour les juristes, Formation à la sécurité des systèmes d'information pour les informaticiens | H24: Utilisation de supports inadaptés qui n’engagent pas les cibles concernées | I24: Moyenne | J24: Messages sécurité ignorés ou non retenus | K24: Utiliser des formats interactifs et gamifiés pour les formations
D25: Enquêtes de compréhension et de satisfaction post-sensibilisation | E25: Des enquêtes de compréhension et de satisfaction post-sensibilisation sont-elles menées ? | F25: PAS | G25: Tableau de bord des indicateurs de participation, Rapport annuel des formations | H25: Manque d’adhésion des utilisateurs aux consignes faute de compréhension | I25: Elevée | J25: Incompréhension des consignes essentielles | K25: Évaluation des connaissances après chaque formation
D26: Suivi des actions de communication interne sur la sécurité | E26: Les actions de communication interne sur la sécurité sont-elles suivies ? | F26: PAS | G26: Registre des absences aux formations, Plan de rattrapage des formations | H26: Diffusion incomplète ou irrégulière des messages, générant des inégalités d’information | I26: Moyenne | J26: Zones d'ombre dans la protection globale | K26: Cartographie dynamique des risques mise à jour trimestriellement
C27: Vérifier que les lignes directrices de la politique de sécurité et des normes de sécurité de l'information sont distribuées à tous les employés et à tous les fournisseurs | D27: Existence d’un canal de diffusion officiel des documents de sécurité | E27: Existe-t-il un canal de diffusion officiel des documents de sécurité ? | F27: PAS | G27: Feuilles de présence, Émargements électroniques | H27: Accès aléatoire aux référentiels, provoquant des erreurs ou des non-conformités | I27: Moyenne | J27: Non-conformité persistante aux standards | K27: Automatisation des contrôles de conformité
D28: Accusé de réception ou signature de lecture des politiques par les employés | E28: Les employés accusent-ils réception ou signent-ils la lecture des politiques ? | F28: PAS | G28: Fiches d'objectifs individuels, Bilan des entretiens annuels | H28: Absence de preuve d’information, difficile à démontrer en cas d’audit ou de contentieux | I28: Elevée | J28: Augmentation des incidents mineurs non traités | K28: Système de classification et priorisation des incidents
D29: Intégration des exigences de sécurité dans les contrats fournisseurs | E29: Les exigences de sécurité sont-elles intégrées dans les contrats fournisseurs ? | F29: PAS | G29: Politique de sanction, Système de récompenses | H29: Engagement contractuel incomplet laissant place à des interprétations floues | I29: Moyenne | J29: Améliorations non capitalisées | K29: Base de connaissance des incidents et solutions
D30: Mise à disposition des normes via l’intranet ou portail collaboratif | E30: Les normes sont-elles mises à disposition via l'intranet ou le portail collaboratif ? | F30: PAS | G30: Guide des procédures de sécurité, Manuel de l'utilisateur | H30: Usage de versions obsolètes des documents de référence | I30: Moyenne | J30: Difficulté à démontrer les progrès | K30: Rapport trimestriel d'avancement avec preuves
D31: Suivi des versions diffusées et personnes destinataires | E31: Les versions diffusées et les personnes destinataires sont-elles suivies ? | F31: PAS | G31: Organigramme fonctionnel, Fiches de poste détaillées | H31: Outils ou formations inadaptés aux profils concernés, rendant les actions inefficaces | I31: Elevée | J31: Manque d'engagement des équipes | K31: Communication régulière par la direction sur l'importance de la sécurité
C32: Vérifier que les acteurs de la sécurité sont formés de manière appropriée ; | D32: Plan de formation spécifique aux rôles de la sécurité (RSSI, techniciens, etc.) | E32: Un plan de formation spécifique aux rôles de la sécurité (RSSI, techniciens, etc.) existe-t-il ? | F32: PAS | G32: Historique des versions des documents, Procédure de gestion des documents | H32: Compétence insuffisante des formateurs, induisant des erreurs dans les pratiques | I32: Elevée | J32: Perte de crédibilité de la fonction sécurité | K32: Nomination d'un sponsor sécurité au comité exécutif
D33: Certification ou qualification des intervenants en sécurité | E33: Les intervenants en sécurité sont-ils certifiés ou qualifiés ? | F33: PAS | G33: Plan de gestion des accès, Plan de gestion de crise | H33: Obsolescence des contenus de formation, rendant les pratiques inadaptées aux menaces actuelles | I33: Faible | J33: Retards dans la prise de décision critique | K33: Désignation claire des pouvoirs en situation de crise
D34: Fréquence et actualisation des modules de formation | E34: Les modules de formation sont-ils fréquents et actualisés ? | F34: OUI | G34: Procès-verbaux des réunions de direction, Circuit de validation des documents | H34: Absence de mesure d’impact, rendant les formations peu exploitables pour le suivi | I34: Faible | J34: Difficulté à établir les responsabilités post-incident | K34: Journal des décisions avec signatures électroniques
D35: Évaluation des compétences acquises post-formation | E35: Les compétences acquises post-formation sont-elles évaluées ? | F35: NON | G35: Système de gestion des demandes de changement, Historique des modifications des actifs | H35: Absence de traçabilité des connaissances acquises et des lacunes persistantes | I35: Faible | J35: Impossibilité de démontrer la diffusion des consignes | K35: Système d'accusé de réception électronique
D36: Suivi individuel des parcours de formation en sécurité | E36: Les parcours de formation en sécurité sont-ils suivis individuellement ? | F36: PAS | G36: Workflow de validation des demandes de changement, Matrice des responsabilités | H36: Manque de visibilité sur l’état global de la sécurité du système d’information | I36: Faible | J36: Erreurs humaines répétées | K36: Simplification des procédures et checklists opérationnelles
C37: Vérifier qu’un système de mesure complet est mis en place afin d'évaluer l'efficacité de la gestion de la sécurité de l'information et pour collecter les suggestions d'amélioration | D37: Tableau de bord de suivi des indicateurs de sécurité de l’information | E37: Un tableau de bord de suivi des indicateurs de sécurité de l'information est-il en place ? | F37: NON | G37: Plan de tests, Rapport de tests | H37: Défaut de contrôle des écarts par rapport aux normes définies | I37: Elevée | J37: Inapplication des règles de base | K37: Audits surprises avec compte-rendu à la direction
D38: Taux de conformité aux politiques et procédures | E38: Le taux de conformité aux politiques et procédures est-il mesuré ? | F38: OUI | G38: Programme d'audit annuel, Rapport d'audit | H38: Accumulation d’incidents non traités ou mal documentés | I38: Faible | J38: Messages contradictoires créant la confusion | K38: Processus de validation centralisé de toute communication sécurité
D39: Nombre et type d’incidents de sécurité enregistrés et résolus | E39: Le nombre et le type d'incidents de sécurité enregistrés et résolus sont-ils suivis ? | F39: NON | G39: Plan de formation à la gestion des changements, Support de formation | H39: Non prise en compte des retours terrain pour améliorer le dispositif | I39: Faible | J39: Niveaux de protection variables selon les services | K39: Programme de standardisation et certification interne
D40: Existence d’un canal de remontée des suggestions d’amélioration | E40: Existe-t-il un canal de remontée des suggestions d'amélioration ? | F40: OUI | G40: Plan de gestion des incidents de sécurité, Référentiel des incidents de sécurité | H40: Risque de répétition des erreurs faute de retour d’expérience exploitable | I40: Faible | J40: Répétition des mêmes incidents de sécurité | K40: Mettre en place une base de connaissances des incidents avec analyse des causes racines
D41: Rapports d’audit ou d’évaluation réguliers avec recommandations suivies | E41: Des rapports d'audit ou d'évaluation réguliers avec recommandations suivies sont-ils produits ? | F41: PAS | G41: Tableau des accords de niveau de service (SLA), Système de gestion des incidents | H41: Difficulté à prouver l’évolution et l’application des recommandations en cas d’incident | I41: Faible | J41: Difficulté à démontrer les améliorations | K41: Créer un système de suivi des recommandations avec preuves de mise en œuvre
B42: Politique de sécurité | C42: S’assurer qu’il existe une politique de sécurité formalisée avec une implication de la direction générale et une définition claire des responsabilités | D42: Existence d’un document officiel de politique de sécurité signé par la direction générale | E42: Existe-t-il un document officiel de politique de sécurité signé par la direction générale ? | F42: PAS | G42: Procédure d'escalade des incidents, Plan de communication de crise | H42: Absence de légitimité du document de politique pouvant réduire l’adhésion des équipes | I42: Elevée | J42: Faible adhésion aux politiques de sécurité | K42: Organiser des ateliers collaboratifs pour co-construire les politiques
D43: Traçabilité des validations ou comités de pilotage impliquant la direction | E43: Les validations ou comités de pilotage impliquant la direction sont-elles traçables ? | F43: NON | G43: Système de gestion des incidents, Rapport d'incident | H43: Manque d’implication de la direction compromettant l’autorité de la démarche sécurité | I43: Faible | J43: Manque de leadership visible sur les enjeux sécurité | K43: Intégrer des objectifs sécurité dans les indicateurs de performance de la direction
D44: Mention explicite des responsabilités au sein de la politique | E44: Les responsabilités sont-elles mentionnées explicitement au sein de la politique ? | F44: NON | G44: Rapport d'analyse post-incident, Plan d'actions correctives | H44: Ambiguïtés sur les responsabilités entraînant des malentendus ou des conflits internes | I44: Moyenne | J44: Conflits récurrents sur les responsabilités | K44: Élaborer et diffuser une matrice RACI détaillée pour la sécurité
D45: Tableau des responsabilités liées à la sécurité par fonction ou service | E45: Un tableau des responsabilités liées à la sécurité par fonction ou service existe-t-il ? | F45: NON | G45: Matrice des rôles et des permissions, Organigramme fonctionnel | H45: Incapacité à identifier rapidement les acteurs responsables en cas de crise | I45: Faible | J45: Retard dans la gestion des crises | K45: Désigner et former des responsables sécurité par domaine avec procédures d'urgence
D46: Archivage des versions antérieures de la politique avec les signatures des parties prenantes | E46: Les versions antérieures de la politique avec les signatures des parties prenantes sont-elles archivées ? | F46: NON | G46: Plan de contrôle d'accès physique, Politique de gestion des accès logiques | H46: Perte d’historique pouvant limiter l’analyse des évolutions ou des responsabilités | I46: Faible | J46: Perte de mémoire organisationnelle | K46: Implémenter un système de gestion documentaire avec historique des versions
C47: S’assurer que la communication se fait à tous les utilisateurs sous une forme pertinente, accessible et compréhensible au lecteur | D47: Support de communication interne (email, intranet, affiches) attestant de la diffusion | E47: Un support de communication interne (email, intranet, affiches) atteste-t-il de la diffusion ? | F47: NON | G47: Programme d'audit annuel, Rapport d'audit | H47: Preuve insuffisante de la diffusion pouvant être reprochée lors d’un audit | I47: Faible | J47: Difficulté à prouver la communication des consignes | K47: Utiliser des outils de diffusion avec accusés de réception et quiz de validation
